Workbook

Sheet customers
A1: CustomerID | B1: Region | C1: CustomerJoinDate
A2: 345e77bf-4a44-4a4c-9b4f-6f5e21e39e8b | B2: East | C2: 45141
A3: c672d9cb-b74b-48ea-bff3-908ff9790632 | B3: West | C3: 44998
A4: 19ebe822-7b55-4146-9fbf-7f30a95fcc27 | B4: West | C4: 45177
A5: 8553b15d-bab5-41e2-b9b1-3bd3e2a7c51e | B5: West | C5: 45033
A6: 2de84462-b349-47ab-8700-7ac254586db9 | B6: West | C6: 44949
A7: cc8645a3-a19b-4915-9cc6-2dce14049120 | B7: West | C7: 45195
A8: 96550947-3cf0-4e17-816e-b347b9a4b83a | B8: East | C8: 45072
A9: 515d5080-8725-4a15-b600-a0b1c9761f39 | B9: West | C9: 45106
A10: 23781516-59fe-4b3b-af71-4d6cb8a012ad | B10: East | C10: 45214
A11: 977445c9-8561-4c71-a03c-ddf327b5dfc2 | B11: West | C11: 45134
A12: ebd558e7-7e80-4319-b5f2-1bbd43d443b7 | B12: East | C12: 45050
A13: 0a5d8031-b5a7-4be4-8d5d-63b70f2a67c7 | B13: East | C13: 45182
... A195: be63b537-602b-468d-8f5b-44bec4d517db | B195: North | C195: 44947

Sheet Products
A1: ProductID | B1: ProductName | C1: ProductCategory | D1: Price | E1: Base_Cost
A2: 1001 | B2: Single-Origin Ethiopian (250g) | C2: Consumables | D2: 19.49 | E2: 11.55
A3: 1002 | B3: Seasonal Blend Light Roast | C3: Consumables | D3: 35.53 | E3: 5.39
A4: 1003 | B4: Decaf Blend (1kg) | C4: Consumables | D4: 40.35 | E4: 11.69
A5: 1004 | B5: Cold Brew Concentrate | C5: Consumables | D5: 23.49 | E5: 9.17
A6: 1005 | B6: Espresso Bean Sampler Pack | C6: Consumables | D6: 19.06 | E6: 10.88
A7: 1006 | B7: Precision Electric Grinder | C7: Grinders & Brewers | D7: 232.2 | E7: 71.26
A8: 1007 | B8: Hand Grinder (Travel Size) | C8: Grinders & Brewers | D8: 254.72 | E8: 118.44
A9: 1008 | B9: Automated Drip Brewer | C9: Grinders & Brewers | D9: 235.76 | E9: 120.44
A10: 1009 | B10: High-Capacity French Press | C10: Grinders & Brewers | D10: 338.36 | E10: 134.7
A11: 1010 | B11: Pour-Over Starter Kit | C11: Grinders & Brewers | D11: 105.23 | E11: 67.95
A12: 1011 | B12: Digital Coffee Scale | C12: Accessories | D12: 26.83 | E12: 13.32
A13: 1012 | B13: Gooseneck Electric Kettle | C13: Accessories | D13: 34.87 | E13: 23.61
... A51: 1050 | B51: Subscription Renewal Service | C51: Subscriptions | D51: 73.41 | E51: 24.81

Sheet Sheet29
A3: ProductName | B3: Sum of Revenue
A4: Airtight Storage Container | B4: 7019.6
A5: Automated Drip Brewer | B5: 28526.96
A6: Bi-Weekly Sampler Box | B6: 13493.04
A7: Branded Ceramic Mug (Large) | B7: 4449.6
A8: Chemex Filters (100 pack) | B8: 2964.3
A9: Cold Brew Concentrate | B9: 2278.53
A10: Daily Grind T-Shirt | B10: 2179.74
A11: Decaf Blend (1kg) | B11: 5003.4
A12: Digital Coffee Scale | B12: 2790.32
A13: Espresso Bean Sampler Pack | B13: 1829.76
A14: Espresso Lovers Quarterly Pack | B14: 8160.83
A15: Gooseneck Electric Kettle | B15: 4149.53
... A29: Grand Total | B29: 235738.29
A34: Product category | B34: Sum of Revenue
A35: Accessories | B35: 19650.44
A36: Grinders & Brewers | B36: 135760.65
A37: Subscriptions | B37: 47108.27
A38: Merchandise | B38: 17717.84
A39: Consumables | B39: 15501.09
A40: Grand Total | B40: 235738.29
A43: Region | B43: Sum of Profit
A44: East | B44: 36608.7
A45: South | B45: 17529.92
A46: West | B46: 53506.48
A47: North | B47: 15947.07
A48: Grand Total | B48: 123592.17

Sheet Orders
A1: OrderID | B1: CustomerID | C1: Product category | D1: ProductName | E1: Region | F1: ProductID | G1: CustomerJoinDate | H1: OrderDate | I1: Quantity | J1: Revenue | K1: COGS | L1: UnitPrice | M1: Profit
A2: 3685c29f-0492-450c-9a61-e93c633ba866 | B2: a1d952b9-ce77-46c9-a08b-f5e62486096f | C2: =_xlfn.XLOOKUP(F2,Products!$A$2:$A$51,Products!$C$2:$C$51,0) -> Accessories | D2: =_xlfn.XLOOKUP(F2,Products!$A$2:$A$51,Products!$B$2:$B$51,0) -> Airtight Storage Container | E2: =_xlfn.XLOOKUP(B2,customers!$A$2:$A$195,customers!$B$2:$B$195,,0) -> East | F2: 1013 | G2: =_xlfn.XLOOKUP(B2,customers!$A$1:$A$195,customers!$C$1:$C$195) -> 45046 | H2: 45658 | I2: 2 | J2: 122.08 | K2: 51.41 | L2: =_xlfn.XLOOKUP(F2,Products!$A$2:$A$51,Products!$D$2:$D$51,0) -> 61.04 | M2: =J2-K2 -> 70.67
A3: f3c573df-56ce-4619-bc05-7c426de7f2ee | B3: cd62b435-4559-412b-9fab-4861a5e87475 | C3: =_xlfn.XLOOKUP(F3,Products!$A$2:$A$51,Products!$C$2:$C$51,0) -> Grinders & Brewers | D3: =_xlfn.XLOOKUP(F3,Products!$A$2:$A$51,Products!$B$2:$B$51,0) -> High-Capacity French Press | E3: =_xlfn.XLOOKUP(B3,customers!$A$2:$A$195,customers!$B$2:$B$195,,0) -> South | F3: 1034 | G3: =_xlfn.XLOOKUP(B3,customers!$A$1:$A$195,customers!$C$1:$C$195) -> 45174 | H3: 45658 | I3: 1 | J3: 338.36 | K3: 148.17 | L3: =_xlfn.XLOOKUP(F3,Products!$A$2:$A$51,Products!$D$2:$D$51,0) -> 338.36 | M3: =J3-K3 -> 190.19
A4: 59abfb23-1d32-4c33-a5b6-cddb1a61780f | B4: 4566cff3-db65-43ab-ad22-32107433a602 | C4: =_xlfn.XLOOKUP(F4,Products!$A$2:$A$51,Products!$C$2:$C$51,0) -> Subscriptions | D4: =_xlfn.XLOOKUP(F4,Products!$A$2:$A$51,Products!$B$2:$B$51,0) -> Subscription Renewal Service | E4: =_xlfn.XLOOKUP(B4,customers!$A$2:$A$195,customers!$B$2:$B$195,,0) -> East | F4: 1050 | G4: =_xlfn.XLOOKUP(B4,customers!$A$1:$A$195,customers!$C$1:$C$195) -> 45264 | H4: 45658 | I4: 4 | J4: 293.64 | K4: 109.16 | L4: =_xlfn.XLOOKUP(F4,Products!$A$2:$A$51,Products!$D$2:$D$51,0) -> 73.41 | M4: =J4-K4 -> 184.48
A5: f85ca148-9dcc-4488-a3ce-48bb5fdb0ad6 | B5: 7f9f3881-a8b6-4a15-a3fb-4f4b7e75e1ef | C5: =_xlfn.XLOOKUP(F5,Products!$A$2:$A$51,Products!$C$2:$C$51,0) -> Subscriptions | D5: =_xlfn.XLOOKUP(F5,Products!$A$2:$A$51,Products!$B$2:$B$51,0) -> Monthly Dark Roast Subscription | E5: =_xlfn.XLOOKUP(B5,customers!$A$2:$A$195,customers!$B$2:$B$195,,0) -> South | F5: 1021 | G5: =_xlfn.XLOOKUP(B5,customers!$A$1:$A$195,customers!$C$1:$C$195) -> 45079 | H5: 45658 | I5: 3 | J5: 183.78 | K5: 105.44 | L5: =_xlfn.XLOOKUP(F5,Products!$A$2:$A$51,Products!$D$2:$D$51,0) -> 61.26 | M5: =J5-K5 -> 78.34
A6: f333a8e1-66ba-46f3-a830-a154afc0e56a | B6: 596febf3-9aa4-4c07-88ab-f7662388e50c | C6: =_xlfn.XLOOKUP(F6,Products!$A$2:$A$51,Products!$C$2:$C$51,0) -> Subscriptions | D6: =_xlfn.XLOOKUP(F6,Products!$A$2:$A$51,Products!$B$2:$B$51,0) -> Espresso Lovers Quarterly Pack | E6: =_xlfn.XLOOKUP(B6,customers!$A$2:$A$195,customers!$B$2:$B$195,,0) -> West | F6: 1024 | G6: =_xlfn.XLOOKUP(B6,customers!$A$1:$A$195,customers!$C$1:$C$195) -> 45193 | H6: 45658 | I6: 3 | J6: 224.61 | K6: 57.58 | L6: =_xlfn.XLOOKUP(F6,Products!$A$2:$A$51,Products!$D$2:$D$51,0) -> 74.87 | M6: =J6-K6 -> 167.03
A7: fb30b1dc-81f6-4030-9dee-516e42a134f6 | B7: c672d9cb-b74b-48ea-bff3-908ff9790632 | C7: =_xlfn.XLOOKUP(F7,Products!$A$2:$A$51,Products!$C$2:$C$51,0) -> Subscriptions | D7: =_xlfn.XLOOKUP(F7,Products!$A$2:$A$51,Products!$B$2:$B$51,0) -> Monthly Dark Roast Subscription | E7: =_xlfn.XLOOKUP(B7,customers!$A$2:$A$195,customers!$B$2:$B$195,,0) -> West | F7: 1046 | G7: =_xlfn.XLOOKUP(B7,customers!$A$1:$A$195,customers!$C$1:$C$195) -> 44998 | H7: 45689 | I7: 1 | J7: 61.26 | K7: 35.15 | L7: =_xlfn.XLOOKUP(F7,Products!$A$2:$A$51,Products!$D$2:$D$51,0) -> 61.26 | M7: =J7-K7 -> 26.11
A8: 715973e8-381f-47ea-9ec0-9ef9a08920ff | B8: dc375298-2549-4d89-b752-d6e8f0a711af | C8: =_xlfn.XLOOKUP(F8,Products!$A$2:$A$51,Products!$C$2:$C$51,0) -> Accessories | D8: =_xlfn.XLOOKUP(F8,Products!$A$2:$A$51,Products!$B$2:$B$51,0) -> Gooseneck Electric Kettle | E8: =_xlfn.XLOOKUP(B8,customers!$A$2:$A$195,customers!$B$2:$B$195,,0) -> North | F8: 1012 | G8: =_xlfn.XLOOKUP(B8,customers!$A$1:$A$195,customers!$C$1:$C$195) -> 45227 | H8: 45689 | I8: 3 | J8: 104.61 | K8: 77.91 | L8: =_xlfn.XLOOKUP(F8,Products!$A$2:$A$51,Products!$D$2:$D$51,0) -> 34.87 | M8: =J8-K8 -> 26.7
A9: fcc2f521-d51e-4965-b29d-f772744667c7 | B9: 8ee81a10-51c3-4f56-82b0-d43244ecdac5 | C9: =_xlfn.XLOOKUP(F9,Products!$A$2:$A$51,Products!$C$2:$C$51,0) -> Subscriptions | D9: =_xlfn.XLOOKUP(F9,Products!$A$2:$A$51,Products!$B$2:$B$51,0) -> Espresso Lovers Quarterly Pack | E9: =_xlfn.XLOOKUP(B9,customers!$A$2:$A$195,customers!$B$2:$B$195,,0) -> East | F9: 1024 | G9: =_xlfn.XLOOKUP(B9,customers!$A$1:$A$195,customers!$C$1:$C$195) -> 45015 | H9: 45689 | I9: 4 | J9: 299.48 | K9: 76.78 | L9: =_xlfn.XLOOKUP(F9,Products!$A$2:$A$51,Products!$D$2:$D$51,0) -> 74.87 | M9: =J9-K9 -> 222.7
A10: f3ab4a96-1727-4306-8d6b-98200dd31748 | B10: 6eb9203d-35ae-4742-bb1e-911b16965477 | C10: =_xlfn.XLOOKUP(F10,Products!$A$2:$A$51,Products!$C$2:$C$51,0) -> Grinders & Brewers | D10: =_xlfn.XLOOKUP(F10,Products!$A$2:$A$51,Products!$B$2:$B$51,0) -> Hand Grinder (Travel Size) | E10: =_xlfn.XLOOKUP(B10,customers!$A$2:$A$195,customers!$B$2:$B$195,,0) -> East | F10: 1032 | G10: =_xlfn.XLOOKUP(B10,customers!$A$1:$A$195,customers!$C$1:$C$195) -> 45251 | H10: 45689 | I10: 1 | J10: 254.72 | K10: 130.28 | L10: =_xlfn.XLOOKUP(F10,Products!$A$2:$A$51,Products!$D$2:$D$51,0) -> 254.72 | M10: =J10-K10 -> 124.44
A11: f67fb8e7-373e-46aa-b512-84abfe710d15 | B11: bf0d6160-338f-4cad-8123-0b5a6763b192 | C11: =_xlfn.XLOOKUP(F11,Products!$A$2:$A$51,Products!$C$2:$C$51,0) -> Grinders & Brewers | D11: =_xlfn.XLOOKUP(F11,Products!$A$2:$A$51,Products!$B$2:$B$51,0) -> Automated Drip Brewer | E11: =_xlfn.XLOOKUP(B11,customers!$A$2:$A$195,customers!$B$2:$B$195,,0) -> South | F11: 1033 | G11: =_xlfn.XLOOKUP(B11,customers!$A$1:$A$195,customers!$C$1:$C$195) -> 45026 | H11: 45717 | I11: 1 | J11: 235.76 | K11: 132.48 | L11: =_xlfn.XLOOKUP(F11,Products!$A$2:$A$51,Products!$D$2:$D$51,0) -> 235.76 | M11: =J11-K11 -> 103.28
A12: a16ee5e4-1df2-4760-8105-7a29fcc11299 | B12: ac0e0eee-04eb-4dd6-bb52-3a2a532b62c0 | C12: =_xlfn.XLOOKUP(F12,Products!$A$2:$A$51,Products!$C$2:$C$51,0) -> Subscriptions | D12: =_xlfn.XLOOKUP(F12,Products!$A$2:$A$51,Products!$B$2:$B$51,0) -> Monthly Dark Roast Subscription | E12: =_xlfn.XLOOKUP(B12,customers!$A$2:$A$195,customers!$B$2:$B$195,,0) -> East | F12: 1021 | G12: =_xlfn.XLOOKUP(B12,customers!$A$1:$A$195,customers!$C$1:$C$195) -> 45239 | H12: 45717 | I12: 1 | J12: 61.26 | K12: 35.15 | L12: =_xlfn.XLOOKUP(F12,Products!$A$2:$A$51,Products!$D$2:$D$51,0) -> 61.26 | M12: =J12-K12 -> 26.11
A13: 1477709f-5755-4892-9a77-fdb2550c0f4f | B13: 515d5080-8725-4a15-b600-a0b1c9761f39 | C13: =_xlfn.XLOOKUP(F13,Products!$A$2:$A$51,Products!$C$2:$C$51,0) -> Merchandise | D13: =_xlfn.XLOOKUP(F13,Products!$A$2:$A$51,Products!$B$2:$B$51,0) -> Daily Grind T-Shirt | E13: =_xlfn.XLOOKUP(B13,customers!$A$2:$A$195,customers!$B$2:$B$195,,0) -> West | F13: 1044 | G13: =_xlfn.XLOOKUP(B13,customers!$A$1:$A$195,customers!$C$1:$C$195) -> 45106 | H13: 45748 | I13: 3 | J13: 64.11 | K13: 24.78 | L13: =_xlfn.XLOOKUP(F13,Products!$A$2:$A$51,Products!$D$2:$D$51,0) -> 21.37 | M13: =J13-K13 -> 39.33
... A35: 505f0b97-f22c-43ab-9a00-a3622efca95f | B35: ee0a4bac-514b-47e0-afb3-0643ed31e7c0 | C35: =_xlfn.XLOOKUP(F35,Products!$A$2:$A$51,Products!$C$2:$C$51,0) -> Subscriptions | D35: =_xlfn.XLOOKUP(F35,Products!$A$2:$A$51,Products!$B$2:$B$51,0) -> Espresso Lovers Quarterly Pack | E35: =_xlfn.XLOOKUP(B35,customers!$A$2:$A$195,customers!$B$2:$B$195,,0) -> East | F35: 1049 | G35: =_xlfn.XLOOKUP(B35,customers!$A$1:$A$195,customers!$C$1:$C$195) -> 45115 | H35: 45931 | I35: 3 | J35: 224.61 | K35: 57.58 | L35: =_xlfn.XLOOKUP(F35,Products!$A$2:$A$51,Products!$D$2:$D$51,0) -> 74.87 | M35: =J35-K35 -> 167.03
A36: a7ccc132-c9f1-4b54-bd29-9f81fb23b5e3 | B36: bbccecfa-0eaa-433d-81c9-1fddba3792d4 | C36: =_xlfn.XLOOKUP(F36,Products!$A$2:$A$51,Products!$C$2:$C$51,0) -> Accessories | D36: =_xlfn.XLOOKUP(F36,Products!$A$2:$A$51,Products!$B$2:$B$51,0) -> Digital Coffee Scale | E36: =_xlfn.XLOOKUP(B36,customers!$A$2:$A$195,customers!$B$2:$B$195,,0) -> West | F36: 1036 | G36: =_xlfn.XLOOKUP(B36,customers!$A$1:$A$195,customers!$C$1:$C$195) -> 45037 | H36: 1/13/2025 | I36: 3 | J36: 80.49 | K36: 43.96 | L36: =_xlfn.XLOOKUP(F36,Products!$A$2:$A$51,Products!$D$2:$D$51,0) -> 26.83 | M36: =J36-K36 -> 36.53
A37: caf0fb18-72e0-4c11-a3c3-9e7434528f44 | B37: d4b53af0-6d06-4d0e-b2e1-b84de575e1c5 | C37: =_xlfn.XLOOKUP(F37,Products!$A$2:$A$51,Products!$C$2:$C$51,0) -> Consumables | D37: =_xlfn.XLOOKUP(F37,Products!$A$2:$A$51,Products!$B$2:$B$51,0) -> Seasonal Blend Light Roast | E37: =_xlfn.XLOOKUP(B37,customers!$A$2:$A$195,customers!$B$2:$B$195,,0) -> North | F37: 1027 | G37: =_xlfn.XLOOKUP(B37,customers!$A$1:$A$195,customers!$C$1:$C$195) -> 45070 | H37: 1/13/2025 | I37: 1 | J37: 35.53 | K37: 5.93 | L37: =_xlfn.XLOOKUP(F37,Products!$A$2:$A$51,Products!$D$2:$D$51,0) -> 35.53 | M37: =J37-K37 -> 29.6
A38: a521ec8a-381d-4739-a765-3ed244b3e9a7 | B38: 46ee2157-1365-44f4-ae66-e5855c3779d7 | C38: =_xlfn.XLOOKUP(F38,Products!$A$2:$A$51,Products!$C$2:$C$51,0) -> Merchandise | D38: =_xlfn.XLOOKUP(F38,Products!$A$2:$A$51,Products!$B$2:$B$51,0) -> Daily Grind T-Shirt | E38: =_xlfn.XLOOKUP(B38,customers!$A$2:$A$195,customers!$B$2:$B$195,,0) -> East | F38: 1044 | G38: =_xlfn.XLOOKUP(B38,customers!$A$1:$A$195,customers!$C$1:$C$195) -> 45262 | H38: 1/13/2025 | I38: 4 | J38: 85.48 | K38: 33.04 | L38: =_xlfn.XLOOKUP(F38,Products!$A$2:$A$51,Products!$D$2:$D$51,0) -> 21.37 | M38: =J38-K38 -> 52.44
A39: b850d516-7c7f-467c-9727-cbefdc6dc599 | B39: e9525326-8155-4e1c-8bad-6dbc399bf3d5 | C39: =_xlfn.XLOOKUP(F39,Products!$A$2:$A$51,Products!$C$2:$C$51,0) -> Consumables | D39: =_xlfn.XLOOKUP(F39,Products!$A$2:$A$51,Products!$B$2:$B$51,0) -> Decaf Blend (1kg) | E39: =_xlfn.XLOOKUP(B39,customers!$A$2:$A$195,customers!$B$2:$B$195,,0) -> West | F39: 1028 | G39: =_xlfn.XLOOKUP(B39,customers!$A$1:$A$195,customers!$C$1:$C$195) -> 45084 | H39: 1/13/2025 | I39: 4 | J39: 161.4 | K39: 51.44 | L39: =_xlfn.XLOOKUP(F39,Products!$A$2:$A$51,Products!$D$2:$D$51,0) -> 40.35 | M39: =J39-K39 -> 109.96
A40: c2ccc14b-7a3a-4d1e-8f41-ad5d4f96b4b8 | B40: 80ff4978-481e-4e21-a861-b4000fe3f313 | C40: =_xlfn.XLOOKUP(F40,Products!$A$2:$A$51,Products!$C$2:$C$51,0) -> Merchandise | D40: =_xlfn.XLOOKUP(F40,Products!$A$2:$A$51,Products!$B$2:$B$51,0) -> Logo Hoodie (Black) | E40: =_xlfn.XLOOKUP(B40,customers!$A$2:$A$195,customers!$B$2:$B$195,,0) -> East | F40: 1042 | G40: =_xlfn.XLOOKUP(B40,customers!$A$1:$A$195,customers!$C$1:$C$195) -> 45276 | H40: 1/14/2025 | I40: 4 | J40: 60.92 | K40: 53.59 | L40: =_xlfn.XLOOKUP(F40,Products!$A$2:$A$51,Products!$D$2:$D$51,0) -> 15.23 | M40: =J40-K40 -> 7.33
A41: 57db7af4-8ccf-4a99-873f-3e558361c69b | B41: 1959deb4-14ea-44cb-b5a1-915e9485b006 | C41: =_xlfn.XLOOKUP(F41,Products!$A$2:$A$51,Products!$C$2:$C$51,0) -> Grinders & Brewers | D41: =_xlfn.XLOOKUP(F41,Products!$A$2:$A$51,Products!$B$2:$B$51,0) -> Pour-Over Starter Kit | E41: =_xlfn.XLOOKUP(B41,customers!$A$2:$A$195,customers!$B$2:$B$195,,0) -> East | F41: 1035 | G41: =_xlfn.XLOOKUP(B41,customers!$A$1:$A$195,customers!$C$1:$C$195) -> 45074 | H41: 1/14/2025 | I41: 2 | J41: 210.46 | K41: 149.49 | L41: =_xlfn.XLOOKUP(F41,Products!$A$2:$A$51,Products!$D$2:$D$51,0) -> 105.23 | M41: =J41-K41 -> 60.97
A42: 7846b8ec-03de-4bac-96ce-64c03a9940c4 | B42: 25d277dc-e796-4782-a7ef-3e1d2fb59188 | C42: =_xlfn.XLOOKUP(F42,Products!$A$2:$A$51,Products!$C$2:$C$51,0) -> Subscriptions | D42: =_xlfn.XLOOKUP(F42,Products!$A$2:$A$51,Products!$B$2:$B$51,0) -> Espresso Lovers Quarterly Pack | E42: =_xlfn.XLOOKUP(B42,customers!$A$2:$A$195,customers!$B$2:$B$195,,0) -> West | F42: 1049 | G42: =_xlfn.XLOOKUP(B42,customers!$A$1:$A$195,customers!$C$1:$C$195) -> 45041 | H42: 1/14/2025 | I42: 1 | J42: 74.87 | K42: 19.2 | L42: =_xlfn.XLOOKUP(F42,Products!$A$2:$A$51,Products!$D$2:$D$51,0) -> 74.87 | M42: =J42-K42 -> 55.67
A43: 1f1da2b2-469d-4733-a4ce-45a1e094adfc | B43: 18405ad5-5712-4ee4-84fd-9e682ad3d596 | C43: =_xlfn.XLOOKUP(F43,Products!$A$2:$A$51,Products!$C$2:$C$51,0) -> Merchandise | D43: =_xlfn.XLOOKUP(F43,Products!$A$2:$A$51,Products!$B$2:$B$51,0) -> Minimalist Keychain | E43: =_xlfn.XLOOKUP(B43,customers!$A$2:$A$195,customers!$B$2:$B$195,,0) -> West | F43: 1020 | G43: =_xlfn.XLOOKUP(B43,customers!$A$1:$A$195,customers!$C$1:$C$195) -> 45166 | H43: 1/14/2025 | I43: 3 | J43: 82.11 | K43: 72.27 | L43: =_xlfn.XLOOKUP(F43,Products!$A$2:$A$51,Products!$D$2:$D$51,0) -> 27.37 | M43: =J43-K43 -> 9.84
A44: 117d5477-ce3a-4229-807e-deb135b0eb6d | B44: 3027e6f9-f285-49fb-93a7-932583102f1b | C44: =_xlfn.XLOOKUP(F44,Products!$A$2:$A$51,Products!$C$2:$C$51,0) -> Consumables | D44: =_xlfn.XLOOKUP(F44,Products!$A$2:$A$51,Products!$B$2:$B$51,0) -> Cold Brew Concentrate | E44: =_xlfn.XLOOKUP(B44,customers!$A$2:$A$195,customers!$B$2:$B$195,,0) -> East | F44: 1004 | G44: =_xlfn.XLOOKUP(B44,customers!$A$1:$A$195,customers!$C$1:$C$195) -> 45171 | H44: 1/15/2025 | I44: 4 | J44: 93.96 | K44: 40.35 | L44: =_xlfn.XLOOKUP(F44,Products!$A$2:$A$51,Products!$D$2:$D$51,0) -> 23.49 | M44: =J44-K44 -> 53.61
A45: ecf82f5d-fd6f-4458-9a8a-afe77914b9b3 | B45: 3aea3b26-9c7a-481d-890c-b9ebb40358e0 | C45: =_xlfn.XLOOKUP(F45,Products!$A$2:$A$51,Products!$C$2:$C$51,0) -> Merchandise | D45: =_xlfn.XLOOKUP(F45,Products!$A$2:$A$51,Products!$B$2:$B$51,0) -> Minimalist Keychain | E45: =_xlfn.XLOOKUP(B45,customers!$A$2:$A$195,customers!$B$2:$B$195,,0) -> North | F45: 1045 | G45: =_xlfn.XLOOKUP(B45,customers!$A$1:$A$195,customers!$C$1:$C$195) -> 45039 | H45: 1/15/2025 | I45: 3 | J45: 82.11 | K45: 72.27 | L45: =_xlfn.XLOOKUP(F45,Products!$A$2:$A$51,Products!$D$2:$D$51,0) -> 27.37 | M45: =J45-K45 -> 9.84
A46: 864c811c-b827-4e0f-8420-bc615a96c99d | B46: d4b53af0-6d06-4d0e-b2e1-b84de575e1c5 | C46: =_xlfn.XLOOKUP(F46,Products!$A$2:$A$51,Products!$C$2:$C$51,0) -> Subscriptions | D46: =_xlfn.XLOOKUP(F46,Products!$A$2:$A$51,Products!$B$2:$B$51,0) -> Subscription Renewal Service | E46: =_xlfn.XLOOKUP(B46,customers!$A$2:$A$195,customers!$B$2:$B$195,,0) -> North | F46: 1050 | G46: =_xlfn.XLOOKUP(B46,customers!$A$1:$A$195,customers!$C$1:$C$195) -> 45070 | H46: 1/16/2025 | I46: 3 | J46: 220.23 | K46: 81.87 | L46: =_xlfn.XLOOKUP(F46,Products!$A$2:$A$51,Products!$D$2:$D$51,0) -> 73.41 | M46: =J46-K46 -> 138.36
A47: fbe8fb57-1729-479e-95c7-825a953dca20 | B47: d84a5bc4-af44-4030-9e24-d893b6f6e966 | C47: =_xlfn.XLOOKUP(F47,Products!$A$2:$A$51,Products!$C$2:$C$51,0) -> Consumables | D47: =_xlfn.XLOOKUP(F47,Products!$A$2:$A$51,Products!$B$2:$B$51,0) -> Single-Origin Ethiopian (250g) | E47: =_xlfn.XLOOKUP(B47,customers!$A$2:$A$195,customers!$B$2:$B$195,,0) -> East | F47: 1001 | G47: =_xlfn.XLOOKUP(B47,customers!$A$1:$A$195,customers!$C$1:$C$195) -> 45272 | H47: 1/17/2025 | I47: 1 | J47: 19.49 | K47: 12.71 | L47: =_xlfn.XLOOKUP(F47,Products!$A$2:$A$51,Products!$D$2:$D$51,0) -> 19.49 | M47: =J47-K47 -> 6.78
... A87: b6871d70-15e2-4b50-ae73-e5d13879d775 | B87: 0e025dda-dcfd-4349-b45d-994ba4664cb3 | C87: =_xlfn.XLOOKUP(F87,Products!$A$2:$A$51,Products!$C$2:$C$51,0) -> Accessories | D87: =_xlfn.XLOOKUP(F87,Products!$A$2:$A$51,Products!$B$2:$B$51,0) -> Airtight Storage Container | E87: =_xlfn.XLOOKUP(B87,customers!$A$2:$A$195,customers!$B$2:$B$195,,0) -> West | F87: 1038 | G87: =_xlfn.XLOOKUP(B87,customers!$A$1:$A$195,customers!$C$1:$C$195) -> 45237 | H87: 1/30/2025 | I87: 4 | J87: 244.16 | K87: 102.83 | L87: =_xlfn.XLOOKUP(F87,Products!$A$2:$A$51,Products!$D$2:$D$51,0) -> 61.04 | M87: =J87-K87 -> 141.33
A88: 6135b1ff-9204-4e49-ad91-2678d7e8c8d1 | B88: b7fd8f42-7477-4c83-ba82-eee3bef2f366 | C88: =_xlfn.XLOOKUP(F88,Products!$A$2:$A$51,Products!$C$2:$C$51,0) -> Grinders & Brewers | D88: =_xlfn.XLOOKUP(F88,Products!$A$2:$A$51,Products!$B$2:$B$51,0) -> Hand Grinder (Travel Size) | E88: =_xlfn.XLOOKUP(B88,customers!$A$2:$A$195,customers!$B$2:$B$195,,0) -> South | F88: 1032 | G88: =_xlfn.XLOOKUP(B88,customers!$A$1:$A$195,customers!$C$1:$C$195) -> 45136 | H88: 45659 | I88: 2 | J88: 509.44 | K88: 260.57 | L88: =_xlfn.XLOOKUP(F88,Products!$A$2:$A$51,Products!$D$2:$D$51,0) -> 254.72 | M88: =J88-K88 -> 248.87
A89: b0107dfd-71ae-4228-ab49-0b38d0dfa016 | B89: 08d68de0-766e-42e3-9145-4e030f805140 | C89: =_xlfn.XLOOKUP(F89,Products!$A$2:$A$51,Products!$C$2:$C$51,0) -> Subscriptions | D89: =_xlfn.XLOOKUP(F89,Products!$A$2:$A$51,Products!$B$2:$B$51,0) -> Monthly Dark Roast Subscription | E89: =_xlfn.XLOOKUP(B89,customers!$A$2:$A$195,customers!$B$2:$B$195,,0) -> East | F89: 1021 | G89: =_xlfn.XLOOKUP(B89,customers!$A$1:$A$195,customers!$C$1:$C$195) -> 45253 | H89: 45690 | I89: 4 | J89: 245.04 | K89: 140.58 | L89: =_xlfn.XLOOKUP(F89,Products!$A$2:$A$51,Products!$D$2:$D$51,0) -> 61.26 | M89: =J89-K89 -> 104.46
A90: 15c6d0c2-ca8e-4d95-a61c-e2bfd438b07e | B90: 345e77bf-4a44-4a4c-9b4f-6f5e21e39e8b | C90: =_xlfn.XLOOKUP(F90,Products!$A$2:$A$51,Products!$C$2:$C$51,0) -> Consumables | D90: =_xlfn.XLOOKUP(F90,Products!$A$2:$A$51,Products!$B$2:$B$51,0) -> Single-Origin Ethiopian (250g) | E90: =_xlfn.XLOOKUP(B90,customers!$A$2:$A$195,customers!$B$2:$B$195,,0) -> East | F90: 1026 | G90: =_xlfn.XLOOKUP(B90,customers!$A$1:$A$195,customers!$C$1:$C$195) -> 45141 | H90: 45718 | I90: 1 | J90: 19.49 | K90: 12.71 | L90: =_xlfn.XLOOKUP(F90,Products!$A$2:$A$51,Products!$D$2:$D$51,0) -> 19.49 | M90: =J90-K90 -> 6.78
A91: 969cea24-b65f-4f57-8159-f3279047b277 | B91: 9db836e7-e5e0-4351-8a5a-37c082766fba | C91: =_xlfn.XLOOKUP(F91,Products!$A$2:$A$51,Products!$C$2:$C$51,0) -> Consumables | D91: =_xlfn.XLOOKUP(F91,Products!$A$2:$A$51,Products!$B$2:$B$51,0) -> Single-Origin Ethiopian (250g) | E91: =_xlfn.XLOOKUP(B91,customers!$A$2:$A$195,customers!$B$2:$B$195,,0) -> East | F91: 1001 | G91: =_xlfn.XLOOKUP(B91,customers!$A$1:$A$195,customers!$C$1:$C$195) -> 45055 | H91: 45718 | I91: 2 | J91: 38.98 | K91: 25.41 | L91: =_xlfn.XLOOKUP(F91,Products!$A$2:$A$51,Products!$D$2:$D$51,0) -> 19.49 | M91: =J91-K91 -> 13.57
A92: 096b3ee9-9aab-4fb5-b77f-da59a44da964 | B92: 39a1dc8b-c9b4-4377-adb6-8eeef78d8192 | C92: =_xlfn.XLOOKUP(F92,Products!$A$2:$A$51,Products!$C$2:$C$51,0) -> Merchandise | D92: =_xlfn.XLOOKUP(F92,Products!$A$2:$A$51,Products!$B$2:$B$51,0) -> Branded Ceramic Mug (Large) | E92: =_xlfn.XLOOKUP(B92,customers!$A$2:$A$195,customers!$B$2:$B$195,,0) -> South | F92: 1041 | G92: =_xlfn.XLOOKUP(B92,customers!$A$1:$A$195,customers!$C$1:$C$195) -> 45204 | H92: 45718 | I92: 1 | J92: 43.2 | K92: 31.11 | L92: =_xlfn.XLOOKUP(F92,Products!$A$2:$A$51,Products!$D$2:$D$51,0) -> 43.2 | M92: =J92-K92 -> 12.09
A93: 5c42f13b-cae6-4bc9-8847-02054b32e90d | B93: 989bc40e-1776-4ea5-892f-d2df497c2608 | C93: =_xlfn.XLOOKUP(F93,Products!$A$2:$A$51,Products!$C$2:$C$51,0) -> Grinders & Brewers | D93: =_xlfn.XLOOKUP(F93,Products!$A$2:$A$51,Products!$B$2:$B$51,0) -> High-Capacity French Press | E93: =_xlfn.XLOOKUP(B93,customers!$A$2:$A$195,customers!$B$2:$B$195,,0) -> North | F93: 1034 | G93: =_xlfn.XLOOKUP(B93,customers!$A$1:$A$195,customers!$C$1:$C$195) -> 45015 | H93: 45718 | I93: 1 | J93: 338.36 | K93: 148.17 | L93: =_xlfn.XLOOKUP(F93,Products!$A$2:$A$51,Products!$D$2:$D$51,0) -> 338.36 | M93: =J93-K93 -> 190.19
A94: bbde17b9-d089-45cf-aa59-4217501aa7fc | B94: d4b53af0-6d06-4d0e-b2e1-b84de575e1c5 | C94: =_xlfn.XLOOKUP(F94,Products!$A$2:$A$51,Products!$C$2:$C$51,0) -> Grinders & Brewers | D94: =_xlfn.XLOOKUP(F94,Products!$A$2:$A$51,Products!$B$2:$B$51,0) -> Precision Electric Grinder | E94: =_xlfn.XLOOKUP(B94,customers!$A$2:$A$195,customers!$B$2:$B$195,,0) -> North | F94: 1031 | G94: =_xlfn.XLOOKUP(B94,customers!$A$1:$A$195,customers!$C$1:$C$195) -> 45070 | H94: 45718 | I94: 1 | J94: 232.2 | K94: 78.39 | L94: =_xlfn.XLOOKUP(F94,Products!$A$2:$A$51,Products!$D$2:$D$51,0) -> 232.2 | M94: =J94-K94 -> 153.81
A95: a629b818-1622-445b-a702-83287074f944 | B95: 2de84462-b349-47ab-8700-7ac254586db9 | C95: =_xlfn.XLOOKUP(F95,Products!$A$2:$A$51,Products!$C$2:$C$51,0) -> Merchandise | D95: =_xlfn.XLOOKUP(F95,Products!$A$2:$A$51,Products!$B$2:$B$51,0) -> Branded Ceramic Mug (Large) | E95: =_xlfn.XLOOKUP(B95,customers!$A$2:$A$195,customers!$B$2:$B$195,,0) -> West | F95: 1016 | G95: =_xlfn.XLOOKUP(B95,customers!$A$1:$A$195,customers!$C$1:$C$195) -> 44949 | H95: 45749 | I95: 4 | J95: 172.8 | K95: 124.43 | L95: =_xlfn.XLOOKUP(F95,Products!$A$2:$A$51,Products!$D$2:$D$51,0) -> 43.2 | M95: =J95-K95 -> 48.37
A96: 688e8939-6612-4b88-b16a-6f5bc17859f5 | B96: e5040015-0c1f-4b62-84e4-6278ebfb2842 | C96: =_xlfn.XLOOKUP(F96,Products!$A$2:$A$51,Products!$C$2:$C$51,0) -> Grinders & Brewers | D96: =_xlfn.XLOOKUP(F96,Products!$A$2:$A$51,Products!$B$2:$B$51,0) -> Automated Drip Brewer | E96: =_xlfn.XLOOKUP(B96,customers!$A$2:$A$195,customers!$B$2:$B$195,,0) -> West | F96: 1008 | G96: =_xlfn.XLOOKUP(B96,customers!$A$1:$A$195,customers!$C$1:$C$195) -> 44982 | H96: 45749 | I96: 2 | J96: 471.52 | K96: 264.97 | L96: =_xlfn.XLOOKUP(F96,Products!$A$2:$A$51,Products!$D$2:$D$51,0) -> 235.76 | M96: =J96-K96 -> 206.55
A97: d19769c4-8d1f-4e01-a02f-abaaea593f36 | B97: 31bd87f8-56a1-4ab6-9a7a-716e19ec8220 | C97: =_xlfn.XLOOKUP(F97,Products!$A$2:$A$51,Products!$C$2:$C$51,0) -> Merchandise | D97: =_xlfn.XLOOKUP(F97,Products!$A$2:$A$51,Products!$B$2:$B$51,0) -> Minimalist Keychain | E97: =_xlfn.XLOOKUP(B97,customers!$A$2:$A$195,customers!$B$2:$B$195,,0) -> East | F97: 1045 | G97: =_xlfn.XLOOKUP(B97,customers!$A$1:$A$195,customers!$C$1:$C$195) -> 45143 | H97: 45749 | I97: 2 | J97: 54.74 | K97: 48.18 | L97: =_xlfn.XLOOKUP(F97,Products!$A$2:$A$51,Products!$D$2:$D$51,0) -> 27.37 | M97: =J97-K97 -> 6.56
A98: 1e32daed-7a1e-4599-9eba-46ac10fb3b29 | B98: d8777a29-8b63-48a6-a4d9-c01a69272eec | C98: =_xlfn.XLOOKUP(F98,Products!$A$2:$A$51,Products!$C$2:$C$51,0) -> Consumables | D98: =_xlfn.XLOOKUP(F98,Products!$A$2:$A$51,Products!$B$2:$B$51,0) -> Decaf Blend (1kg) | E98: =_xlfn.XLOOKUP(B98,customers!$A$2:$A$195,customers!$B$2:$B$195,,0) -> West | F98: 1003 | G98: =_xlfn.XLOOKUP(B98,customers!$A$1:$A$195,customers!$C$1:$C$195) -> 45132 | H98: 45749 | I98: 3 | J98: 121.05 | K98: 38.58 | L98: =_xlfn.XLOOKUP(F98,Products!$A$2:$A$51,Products!$D$2:$D$51,0) -> 40.35 | M98: =J98-K98 -> 82.47
A99: 0cec6677-5993-4be9-92ab-78bc1311280f | B99: c773874c-adcd-4b21-9d8f-f72f3b3cb8eb | C99: =_xlfn.XLOOKUP(F99,Products!$A$2:$A$51,Products!$C$2:$C$51,0) -> Accessories | D99: =_xlfn.XLOOKUP(F99,Products!$A$2:$A$51,Products!$B$2:$B$51,0) -> Chemex Filters (100 pack) | E99: =_xlfn.XLOOKUP(B99,customers!$A$2:$A$195,customers!$B$2:$B$195,,0) -> West | F99: 1014 | G99: =_xlfn.XLOOKUP(B99,customers!$A$1:$A$195,customers!$C$1:$C$195) -> 45216 | H99: 45749 | I99: 4 | J99: 96.4 | K99: 84.83 | L99: =_xlfn.XLOOKUP(F99,Products!$A$2:$A$51,Products!$D$2:$D$51,0) -> 24.1 | M99: =J99-K99 -> 11.57
... A130: c7c55120-961e-4a21-a5cd-0daf2d89d19a | B130: 4c71f46b-aec0-4b76-92c5-beda74b59e13 | C130: =_xlfn.XLOOKUP(F130,Products!$A$2:$A$51,Products!$C$2:$C$51,0) -> Merchandise | D130: =_xlfn.XLOOKUP(F130,Products!$A$2:$A$51,Products!$B$2:$B$51,0) -> Minimalist Keychain | E130: =_xlfn.XLOOKUP(B130,customers!$A$2:$A$195,customers!$B$2:$B$195,,0) -> West | F130: 1045 | G130: =_xlfn.XLOOKUP(B130,customers!$A$1:$A$195,customers!$C$1:$C$195) -> 45282 | H130: 45993 | I130: 1 | J130: 27.37 | K130: 24.09 | L130: =_xlfn.XLOOKUP(F130,Products!$A$2:$A$51,Products!$D$2:$D$51,0) -> 27.37 | M130: =J130-K130 -> 3.28
A131: b4839f50-269a-4ff2-b6ca-cdc26f781b0e | B131: e5040015-0c1f-4b62-84e4-6278ebfb2842 | C131: =_xlfn.XLOOKUP(F131,Products!$A$2:$A$51,Products!$C$2:$C$51,0) -> Grinders & Brewers | D131: =_xlfn.XLOOKUP(F131,Products!$A$2:$A$51,Products!$B$2:$B$51,0) -> Precision Electric Grinder | E131: =_xlfn.XLOOKUP(B131,customers!$A$2:$A$195,customers!$B$2:$B$195,,0) -> West | F131: 1031 | G131: =_xlfn.XLOOKUP(B131,customers!$A$1:$A$195,customers!$C$1:$C$195) -> 44982 | H131: 2/13/2025 | I131: 1 | J131: 232.2 | K131: 78.39 | L131: =_xlfn.XLOOKUP(F131,Products!$A$2:$A$51,Products!$D$2:$D$51,0) -> 232.2 | M131: =J131-K131 -> 153.81
A132: 8ccfddfe-8b96-4354-a8a6-4460aedb2d57 | B132: 98c0cbd2-519c-4482-9c03-a77f16684ab1 | C132: =_xlfn.XLOOKUP(F132,Products!$A$2:$A$51,Products!$C$2:$C$51,0) -> Subscriptions | D132: =_xlfn.XLOOKUP(F132,Products!$A$2:$A$51,Products!$B$2:$B$51,0) -> Subscription Renewal Service | E132: =_xlfn.XLOOKUP(B132,customers!$A$2:$A$195,customers!$B$2:$B$195,,0) -> West | F132: 1050 | G132: =_xlfn.XLOOKUP(B132,customers!$A$1:$A$195,customers!$C$1:$C$195) -> 44947 | H132: 2/13/2025 | I132: 2 | J132: 146.82 | K132: 54.58 | L132: =_xlfn.XLOOKUP(F132,Products!$A$2:$A$51,Products!$D$2:$D$51,0) -> 73.41 | M132: =J132-K132 -> 92.24
A133: f5fd8e3c-75cf-485b-aa13-71596d7a363f | B133: 8b37abf3-4486-4871-8768-982d137116f5 | C133: =_xlfn.XLOOKUP(F133,Products!$A$2:$A$51,Products!$C$2:$C$51,0) -> Accessories | D133: =_xlfn.XLOOKUP(F133,Products!$A$2:$A$51,Products!$B$2:$B$51,0) -> Chemex Filters (100 pack) | E133: =_xlfn.XLOOKUP(B133,customers!$A$2:$A$195,customers!$B$2:$B$195,,0) -> South | F133: 1014 | G133: =_xlfn.XLOOKUP(B133,customers!$A$1:$A$195,customers!$C$1:$C$195) -> 45221 | H133: 2/13/2025 | I133: 3 | J133: 72.3 | K133: 63.62 | L133: =_xlfn.XLOOKUP(F133,Products!$A$2:$A$51,Products!$D$2:$D$51,0) -> 24.1 | M133: =J133-K133 -> 8.68
A134: 72e9358d-afc2-4e39-aff8-433db2175b00 | B134: d960ec46-3288-4c77-82ec-5c1304a160ee | C134: =_xlfn.XLOOKUP(F134,Products!$A$2:$A$51,Products!$C$2:$C$51,0) -> Consumables | D134: =_xlfn.XLOOKUP(F134,Products!$A$2:$A$51,Products!$B$2:$B$51,0) -> Seasonal Blend Light Roast | E134: =_xlfn.XLOOKUP(B134,customers!$A$2:$A$195,customers!$B$2:$B$195,,0) -> South | F134: 1027 | G134: =_xlfn.XLOOKUP(B134,customers!$A$1:$A$195,customers!$C$1:$C$195) -> 45059 | H134: 2/14/2025 | I134: 1 | J134: 35.53 | K134: 5.93 | L134: =_xlfn.XLOOKUP(F134,Products!$A$2:$A$51,Products!$D$2:$D$51,0) -> 35.53 | M134: =J134-K134 -> 29.6
A135: 5558ea85-d76a-4447-b4c1-0dc8254b1fff | B135: 843aafe5-e9e0-4c4e-88c3-15357434a75d | C135: =_xlfn.XLOOKUP(F135,Products!$A$2:$A$51,Products!$C$2:$C$51,0) -> Grinders & Brewers | D135: =_xlfn.XLOOKUP(F135,Products!$A$2:$A$51,Products!$B$2:$B$51,0) -> Hand Grinder (Travel Size) | E135: =_xlfn.XLOOKUP(B135,customers!$A$2:$A$195,customers!$B$2:$B$195,,0) -> East | F135: 1032 | G135: =_xlfn.XLOOKUP(B135,customers!$A$1:$A$195,customers!$C$1:$C$195) -> 45068 | H135: 2/14/2025 | I135: 1 | J135: 254.72 | K135: 130.28 | L135: =_xlfn.XLOOKUP(F135,Products!$A$2:$A$51,Products!$D$2:$D$51,0) -> 254.72 | M135: =J135-K135 -> 124.44
A136: 63db0a94-4075-4754-9f69-03cb979474a5 | B136: 0e24031a-213b-4ac8-aba2-ca13e1134488 | C136: =_xlfn.XLOOKUP(F136,Products!$A$2:$A$51,Products!$C$2:$C$51,0) -> Accessories | D136: =_xlfn.XLOOKUP(F136,Products!$A$2:$A$51,Products!$B$2:$B$51,0) -> Digital Coffee Scale | E136: =_xlfn.XLOOKUP(B136,customers!$A$2:$A$195,customers!$B$2:$B$195,,0) -> East | F136: 1011 | G136: =_xlfn.XLOOKUP(B136,customers!$A$1:$A$195,customers!$C$1:$C$195) -> 45286 | H136: 2/14/2025 | I136: 2 | J136: 53.66 | K136: 29.3 | L136: =_xlfn.XLOOKUP(F136,Products!$A$2:$A$51,Products!$D$2:$D$51,0) -> 26.83 | M136: =J136-K136 -> 24.36
A137: 4957b29f-6bd3-4d3a-be73-7bd3d7352ddf | B137: 55bc49dc-a542-49a5-ab7d-60463db9fb46 | C137: =_xlfn.XLOOKUP(F137,Products!$A$2:$A$51,Products!$C$2:$C$51,0) -> Grinders & Brewers | D137: =_xlfn.XLOOKUP(F137,Products!$A$2:$A$51,Products!$B$2:$B$51,0) -> Automated Drip Brewer | E137: =_xlfn.XLOOKUP(B137,customers!$A$2:$A$195,customers!$B$2:$B$195,,0) -> South | F137: 1033 | G137: =_xlfn.XLOOKUP(B137,customers!$A$1:$A$195,customers!$C$1:$C$195) -> 44978 | H137: 2/15/2025 | I137: 3 | J137: 707.28 | K137: 397.45 | L137: =_xlfn.XLOOKUP(F137,Products!$A$2:$A$51,Products!$D$2:$D$51,0) -> 235.76 | M137: =J137-K137 -> 309.83
A138: 21978a52-ae70-483e-a1b1-9a2165d145b0 | B138: 66d3d64f-ce87-4119-bed2-2ca019d60c79 | C138: =_xlfn.XLOOKUP(F138,Products!$A$2:$A$51,Products!$C$2:$C$51,0) -> Subscriptions | D138: =_xlfn.XLOOKUP(F138,Products!$A$2:$A$51,Products!$B$2:$B$51,0) -> Bi-Weekly Sampler Box | E138: =_xlfn.XLOOKUP(B138,customers!$A$2:$A$195,customers!$B$2:$B$195,,0) -> South | F138: 1047 | G138: =_xlfn.XLOOKUP(B138,customers!$A$1:$A$195,customers!$C$1:$C$195) -> 45252 | H138: 2/15/2025 | I138: 4 | J138: 355.08 | K138: 95.44 | L138: =_xlfn.XLOOKUP(F138,Products!$A$2:$A$51,Products!$D$2:$D$51,0) -> 88.77 | M138: =J138-K138 -> 259.64
A139: d23a795f-a8ee-479d-b7e7-8c39b3b787c8 | B139: 345e77bf-4a44-4a4c-9b4f-6f5e21e39e8b | C139: =_xlfn.XLOOKUP(F139,Products!$A$2:$A$51,Products!$C$2:$C$51,0) -> Merchandise | D139: =_xlfn.XLOOKUP(F139,Products!$A$2:$A$51,Products!$B$2:$B$51,0) -> Branded Ceramic Mug (Large) | E139: =_xlfn.XLOOKUP(B139,customers!$A$2:$A$195,customers!$B$2:$B$195,,0) -> East | F139: 1016 | G139: =_xlfn.XLOOKUP(B139,customers!$A$1:$A$195,customers!$C$1:$C$195) -> 45141 | H139: 2/17/2025 | I139: 3 | J139: 129.6 | K139: 93.32 | L139: =_xlfn.XLOOKUP(F139,Products!$A$2:$A$51,Products!$D$2:$D$51,0) -> 43.2 | M139: =J139-K139 -> 36.28
A140: ac62a7ad-4f84-477d-bda3-a751e0e2717c | B140: 515d5080-8725-4a15-b600-a0b1c9761f39 | C140: =_xlfn.XLOOKUP(F140,Products!$A$2:$A$51,Products!$C$2:$C$51,0) -> Grinders & Brewers | D140: =_xlfn.XLOOKUP(F140,Products!$A$2:$A$51,Products!$B$2:$B$51,0) -> Automated Drip Brewer | E140: =_xlfn.XLOOKUP(B140,customers!$A$2:$A$195,customers!$B$2:$B$195,,0) -> West | F140: 1008 | G140: =_xlfn.XLOOKUP(B140,customers!$A$1:$A$195,customers!$C$1:$C$195) -> 45106 | H140: 2/17/2025 | I140: 2 | J140: 471.52 | K140: 264.97 | L140: =_xlfn.XLOOKUP(F140,Products!$A$2:$A$51,Products!$D$2:$D$51,0) -> 235.76 | M140: =J140-K140 -> 206.55
A141: bab7b353-c46b-41c5-8613-dcc52052684c | B141: 23781516-59fe-4b3b-af71-4d6cb8a012ad | C141: =_xlfn.XLOOKUP(F141,Products!$A$2:$A$51,Products!$C$2:$C$51,0) -> Merchandise | D141: =_xlfn.XLOOKUP(F141,Products!$A$2:$A$51,Products!$B$2:$B$51,0) -> Insulated Travel Tumbler | E141: =_xlfn.XLOOKUP(B141,customers!$A$2:$A$195,customers!$B$2:$B$195,,0) -> East | F141: 1043 | G141: =_xlfn.XLOOKUP(B141,customers!$A$1:$A$195,customers!$C$1:$C$195) -> 45214 | H141: 2/17/2025 | I141: 4 | J141: 173.12 | K141: 83.29 | L141: =_xlfn.XLOOKUP(F141,Products!$A$2:$A$51,Products!$D$2:$D$51,0) -> 43.28 | M141: =J141-K141 -> 89.83
A142: 58a12134-decf-4f28-a4a6-ff697c0373a4 | B142: ab8adb41-5ec5-456d-a160-a01affd920c4 | C142: =_xlfn.XLOOKUP(F142,Products!$A$2:$A$51,Products!$C$2:$C$51,0) -> Consumables | D142: =_xlfn.XLOOKUP(F142,Products!$A$2:$A$51,Products!$B$2:$B$51,0) -> Decaf Blend (1kg) | E142: =_xlfn.XLOOKUP(B142,customers!$A$2:$A$195,customers!$B$2:$B$195,,0) -> West | F142: 1003 | G142: =_xlfn.XLOOKUP(B142,customers!$A$1:$A$195,customers!$C$1:$C$195) -> 45069 | H142: 2/17/2025 | I142: 3 | J142: 121.05 | K142: 38.58 | L142: =_xlfn.XLOOKUP(F142,Products!$A$2:$A$51,Products!$D$2:$D$51,0) -> 40.35 | M142: =J142-K142 -> 82.47
... A179: 20ab3646-caa5-4606-8d0d-cb85874cf542 | B179: 18bce6d7-de06-47c3-87dc-67dc5c8ffe62 | C179: =_xlfn.XLOOKUP(F179,Products!$A$2:$A$51,Products!$C$2:$C$51,0) -> Accessories | D179: =_xlfn.XLOOKUP(F179,Products!$A$2:$A$51,Products!$B$2:$B$51,0) -> Chemex Filters (100 pack) | E179: =_xlfn.XLOOKUP(B179,customers!$A$2:$A$195,customers!$B$2:$B$195,,0) -> North | F179: 1014 | G179: =_xlfn.XLOOKUP(B179,customers!$A$1:$A$195,customers!$C$1:$C$195) -> 45234 | H179: 2/28/2025 | I179: 2 | J179: 48.2 | K179: 42.42 | L179: =_xlfn.XLOOKUP(F179,Products!$A$2:$A$51,Products!$D$2:$D$51,0) -> 24.1 | M179: =J179-K179 -> 5.78
A180: d749ea8d-3b78-4ca1-82b8-8355be93b44d | B180: 889b8d90-6fd7-4dc5-b0d7-6fdce37da4c0 | C180: =_xlfn.XLOOKUP(F180,Products!$A$2:$A$51,Products!$C$2:$C$51,0) -> Merchandise | D180: =_xlfn.XLOOKUP(F180,Products!$A$2:$A$51,Products!$B$2:$B$51,0) -> Insulated Travel Tumbler | E180: =_xlfn.XLOOKUP(B180,customers!$A$2:$A$195,customers!$B$2:$B$195,,0) -> North | F180: 1018 | G180: =_xlfn.XLOOKUP(B180,customers!$A$1:$A$195,customers!$C$1:$C$195) -> 45090 | H180: 45660 | I180: 2 | J180: 86.56 | K180: 41.65 | L180: =_xlfn.XLOOKUP(F180,Products!$A$2:$A$51,Products!$D$2:$D$51,0) -> 43.28 | M180: =J180-K180 -> 44.91
A181: 9d4563a2-78e8-461b-8b59-6e5d22aac38f | B181: 3027e6f9-f285-49fb-93a7-932583102f1b | C181: =_xlfn.XLOOKUP(F181,Products!$A$2:$A$51,Products!$C$2:$C$51,0) -> Subscriptions | D181: =_xlfn.XLOOKUP(F181,Products!$A$2:$A$51,Products!$B$2:$B$51,0) -> Subscription Renewal Service | E181: =_xlfn.XLOOKUP(B181,customers!$A$2:$A$195,customers!$B$2:$B$195,,0) -> East | F181: 1025 | G181: =_xlfn.XLOOKUP(B181,customers!$A$1:$A$195,customers!$C$1:$C$195) -> 45171 | H181: 45691 | I181: 1 | J181: 73.41 | K181: 27.29 | L181: =_xlfn.XLOOKUP(F181,Products!$A$2:$A$51,Products!$D$2:$D$51,0) -> 73.41 | M181: =J181-K181 -> 46.12
A182: 4aa161f6-a747-43a0-bfb3-968c5a358b02 | B182: 6a60908f-c782-4a70-9760-68affc310ed5 | C182: =_xlfn.XLOOKUP(F182,Products!$A$2:$A$51,Products!$C$2:$C$51,0) -> Accessories | D182: =_xlfn.XLOOKUP(F182,Products!$A$2:$A$51,Products!$B$2:$B$51,0) -> Digital Coffee Scale | E182: =_xlfn.XLOOKUP(B182,customers!$A$2:$A$195,customers!$B$2:$B$195,,0) -> West | F182: 1011 | G182: =_xlfn.XLOOKUP(B182,customers!$A$1:$A$195,customers!$C$1:$C$195) -> 44943 | H182: 45691 | I182: 2 | J182: 53.66 | K182: 29.3 | L182: =_xlfn.XLOOKUP(F182,Products!$A$2:$A$51,Products!$D$2:$D$51,0) -> 26.83 | M182: =J182-K182 -> 24.36
A183: 1c7a08bd-ecfd-4af5-b61e-627d5b9dc018 | B183: 51eea915-f3d3-4c3e-bd09-f158a0f182e6 | C183: =_xlfn.XLOOKUP(F183,Products!$A$2:$A$51,Products!$C$2:$C$51,0) -> Grinders & Brewers | D183: =_xlfn.XLOOKUP(F183,Products!$A$2:$A$51,Products!$B$2:$B$51,0) -> Hand Grinder (Travel Size) | E183: =_xlfn.XLOOKUP(B183,customers!$A$2:$A$195,customers!$B$2:$B$195,,0) -> East | F183: 1032 | G183: =_xlfn.XLOOKUP(B183,customers!$A$1:$A$195,customers!$C$1:$C$195) -> 45149 | H183: 45691 | I183: 1 | J183: 254.72 | K183: 130.28 | L183: =_xlfn.XLOOKUP(F183,Products!$A$2:$A$51,Products!$D$2:$D$51,0) -> 254.72 | M183: =J183-K183 -> 124.44
A184: e4d330ed-049b-45bc-9b1a-215092d969f5 | B184: 868ce574-ced2-49c2-a90a-6e89e6640934 | C184: =_xlfn.XLOOKUP(F184,Products!$A$2:$A$51,Products!$C$2:$C$51,0) -> Consumables | D184: =_xlfn.XLOOKUP(F184,Products!$A$2:$A$51,Products!$B$2:$B$51,0) -> Single-Origin Ethiopian (250g) | E184: =_xlfn.XLOOKUP(B184,customers!$A$2:$A$195,customers!$B$2:$B$195,,0) -> West | F184: 1001 | G184: =_xlfn.XLOOKUP(B184,customers!$A$1:$A$195,customers!$C$1:$C$195) -> 45152 | H184: 45719 | I184: 4 | J184: 77.96 | K184: 50.82 | L184: =_xlfn.XLOOKUP(F184,Products!$A$2:$A$51,Products!$D$2:$D$51,0) -> 19.49 | M184: =J184-K184 -> 27.14
A185: f7af8f0d-57d6-4fb1-afdb-7adcb334ffe3 | B185: be63b537-602b-468d-8f5b-44bec4d517db | C185: =_xlfn.XLOOKUP(F185,Products!$A$2:$A$51,Products!$C$2:$C$51,0) -> Merchandise | D185: =_xlfn.XLOOKUP(F185,Products!$A$2:$A$51,Products!$B$2:$B$51,0) -> Daily Grind T-Shirt | E185: =_xlfn.XLOOKUP(B185,customers!$A$2:$A$195,customers!$B$2:$B$195,,0) -> North | F185: 1019 | G185: =_xlfn.XLOOKUP(B185,customers!$A$1:$A$195,customers!$C$1:$C$195) -> 44947 | H185: 45719 | I185: 1 | J185: 21.37 | K185: 8.26 | L185: =_xlfn.XLOOKUP(F185,Products!$A$2:$A$51,Products!$D$2:$D$51,0) -> 21.37 | M185: =J185-K185 -> 13.11
A186: dfdb0058-1b30-41df-88f1-a19aafe86f44 | B186: cd62b435-4559-412b-9fab-4861a5e87475 | C186: =_xlfn.XLOOKUP(F186,Products!$A$2:$A$51,Products!$C$2:$C$51,0) -> Grinders & Brewers | D186: =_xlfn.XLOOKUP(F186,Products!$A$2:$A$51,Products!$B$2:$B$51,0) -> High-Capacity French Press | E186: =_xlfn.XLOOKUP(B186,customers!$A$2:$A$195,customers!$B$2:$B$195,,0) -> South | F186: 1034 | G186: =_xlfn.XLOOKUP(B186,customers!$A$1:$A$195,customers!$C$1:$C$195) -> 45174 | H186: 45750 | I186: 4 | J186: 1353.44 | K186: 592.68 | L186: =_xlfn.XLOOKUP(F186,Products!$A$2:$A$51,Products!$D$2:$D$51,0) -> 338.36 | M186: =J186-K186 -> 760.76
A187: 8c468ce1-9190-44ff-b761-dc638e094c8a | B187: 0518f99d-8e5b-496f-9c0b-34f0c24ee49f | C187: =_xlfn.XLOOKUP(F187,Products!$A$2:$A$51,Products!$C$2:$C$51,0) -> Grinders & Brewers | D187: =_xlfn.XLOOKUP(F187,Products!$A$2:$A$51,Products!$B$2:$B$51,0) -> Pour-Over Starter Kit | E187: =_xlfn.XLOOKUP(B187,customers!$A$2:$A$195,customers!$B$2:$B$195,,0) -> West | F187: 1010 | G187: =_xlfn.XLOOKUP(B187,customers!$A$1:$A$195,customers!$C$1:$C$195) -> 45132 | H187: 45750 | I187: 2 | J187: 210.46 | K187: 149.49 | L187: =_xlfn.XLOOKUP(F187,Products!$A$2:$A$51,Products!$D$2:$D$51,0) -> 105.23 | M187: =J187-K187 -> 60.97
A188: b2429686-79a2-4af8-8756-59b75b10da27 | B188: 432f9bfc-4c2f-4748-850a-90f385eef86e | C188: =_xlfn.XLOOKUP(F188,Products!$A$2:$A$51,Products!$C$2:$C$51,0) -> Grinders & Brewers | D188: =_xlfn.XLOOKUP(F188,Products!$A$2:$A$51,Products!$B$2:$B$51,0) -> Hand Grinder (Travel Size) | E188: =_xlfn.XLOOKUP(B188,customers!$A$2:$A$195,customers!$B$2:$B$195,,0) -> North | F188: 1032 | G188: =_xlfn.XLOOKUP(B188,customers!$A$1:$A$195,customers!$C$1:$C$195) -> 44961 | H188: 45780 | I188: 1 | J188: 254.72 | K188: 130.28 | L188: =_xlfn.XLOOKUP(F188,Products!$A$2:$A$51,Products!$D$2:$D$51,0) -> 254.72 | M188: =J188-K188 -> 124.44
A189: f488efd8-2eaf-4852-b2e1-5022c02d090f | B189: fcd08e95-2618-4bc4-9e53-a3a4cfe97e16 | C189: =_xlfn.XLOOKUP(F189,Products!$A$2:$A$51,Products!$C$2:$C$51,0) -> Grinders & Brewers | D189: =_xlfn.XLOOKUP(F189,Products!$A$2:$A$51,Products!$B$2:$B$51,0) -> Automated Drip Brewer | E189: =_xlfn.XLOOKUP(B189,customers!$A$2:$A$195,customers!$B$2:$B$195,,0) -> North | F189: 1033 | G189: =_xlfn.XLOOKUP(B189,customers!$A$1:$A$195,customers!$C$1:$C$195) -> 45129 | H189: 45780 | I189: 3 | J189: 707.28 | K189: 397.45 | L189: =_xlfn.XLOOKUP(F189,Products!$A$2:$A$51,Products!$D$2:$D$51,0) -> 235.76 | M189: =J189-K189 -> 309.83
A190: cbd11115-612a-42f1-8ca1-ff7f3c61f95d | B190: 977445c9-8561-4c71-a03c-ddf327b5dfc2 | C190: =_xlfn.XLOOKUP(F190,Products!$A$2:$A$51,Products!$C$2:$C$51,0) -> Merchandise | D190: =_xlfn.XLOOKUP(F190,Products!$A$2:$A$51,Products!$B$2:$B$51,0) -> Branded Ceramic Mug (Large) | E190: =_xlfn.XLOOKUP(B190,customers!$A$2:$A$195,customers!$B$2:$B$195,,0) -> West | F190: 1041 | G190: =_xlfn.XLOOKUP(B190,customers!$A$1:$A$195,customers!$C$1:$C$195) -> 45134 | H190: 45811 | I190: 2 | J190: 86.4 | K190: 62.22 | L190: =_xlfn.XLOOKUP(F190,Products!$A$2:$A$51,Products!$D$2:$D$51,0) -> 43.2 | M190: =J190-K190 -> 24.18
A191: 00a091f1-36f9-4571-97b9-f875dfbe22bf | B191: a1d952b9-ce77-46c9-a08b-f5e62486096f | C191: =_xlfn.XLOOKUP(F191,Products!$A$2:$A$51,Products!$C$2:$C$51,0) -> Grinders & Brewers | D191: =_xlfn.XLOOKUP(F191,Products!$A$2:$A$51,Products!$B$2:$B$51,0) -> High-Capacity French Press | E191: =_xlfn.XLOOKUP(B191,customers!$A$2:$A$195,customers!$B$2:$B$195,,0) -> East | F191: 1034 | G191: =_xlfn.XLOOKUP(B191,customers!$A$1:$A$195,customers!$C$1:$C$195) -> 45046 | H191: 45811 | I191: 2 | J191: 676.72 | K191: 296.34 | L191: =_xlfn.XLOOKUP(F191,Products!$A$2:$A$51,Products!$D$2:$D$51,0) -> 338.36 | M191: =J191-K191 -> 380.38
... A209: 423e6f19-aa56-431c-a26d-bb3ebecd7407 | B209: c773874c-adcd-4b21-9d8f-f72f3b3cb8eb | C209: =_xlfn.XLOOKUP(F209,Products!$A$2:$A$51,Products!$C$2:$C$51,0) -> Grinders & Brewers | D209: =_xlfn.XLOOKUP(F209,Products!$A$2:$A$51,Products!$B$2:$B$51,0) -> High-Capacity French Press | E209: =_xlfn.XLOOKUP(B209,customers!$A$2:$A$195,customers!$B$2:$B$195,,0) -> West | F209: 1009 | G209: =_xlfn.XLOOKUP(B209,customers!$A$1:$A$195,customers!$C$1:$C$195) -> 45216 | H209: 45994 | I209: 3 | J209: 1015.08 | K209: 444.51 | L209: =_xlfn.XLOOKUP(F209,Products!$A$2:$A$51,Products!$D$2:$D$51,0) -> 338.36 | M209: =J209-K209 -> 570.57
A210: bc575cb5-db1a-4e51-a066-69f6e0b14995 | B210: 977445c9-8561-4c71-a03c-ddf327b5dfc2 | C210: =_xlfn.XLOOKUP(F210,Products!$A$2:$A$51,Products!$C$2:$C$51,0) -> Merchandise | D210: =_xlfn.XLOOKUP(F210,Products!$A$2:$A$51,Products!$B$2:$B$51,0) -> Minimalist Keychain | E210: =_xlfn.XLOOKUP(B210,customers!$A$2:$A$195,customers!$B$2:$B$195,,0) -> West | F210: 1045 | G210: =_xlfn.XLOOKUP(B210,customers!$A$1:$A$195,customers!$C$1:$C$195) -> 45134 | H210: 3/13/2025 | I210: 3 | J210: 82.11 | K210: 72.27 | L210: =_xlfn.XLOOKUP(F210,Products!$A$2:$A$51,Products!$D$2:$D$51,0) -> 27.37 | M210: =J210-K210 -> 9.84
A211: a439bddb-d0e8-4e48-9a74-02df69469229 | B211: 4661672e-252f-4297-8b05-ba339f296241 | C211: =_xlfn.XLOOKUP(F211,Products!$A$2:$A$51,Products!$C$2:$C$51,0) -> Grinders & Brewers | D211: =_xlfn.XLOOKUP(F211,Products!$A$2:$A$51,Products!$B$2:$B$51,0) -> Automated Drip Brewer | E211: =_xlfn.XLOOKUP(B211,customers!$A$2:$A$195,customers!$B$2:$B$195,,0) -> West | F211: 1008 | G211: =_xlfn.XLOOKUP(B211,customers!$A$1:$A$195,customers!$C$1:$C$195) -> 44967 | H211: 3/13/2025 | I211: 1 | J211: 235.76 | K211: 132.48 | L211: =_xlfn.XLOOKUP(F211,Products!$A$2:$A$51,Products!$D$2:$D$51,0) -> 235.76 | M211: =J211-K211 -> 103.28
A212: 3c88a9a2-9292-408b-9138-d9a6435c08e1 | B212: 42b384aa-9070-4b83-bab4-3a016da0af40 | C212: =_xlfn.XLOOKUP(F212,Products!$A$2:$A$51,Products!$C$2:$C$51,0) -> Subscriptions | D212: =_xlfn.XLOOKUP(F212,Products!$A$2:$A$51,Products!$B$2:$B$51,0) -> Three-Month Gift Subscription | E212: =_xlfn.XLOOKUP(B212,customers!$A$2:$A$195,customers!$B$2:$B$195,,0) -> East | F212: 1048 | G212: =_xlfn.XLOOKUP(B212,customers!$A$1:$A$195,customers!$C$1:$C$195) -> 45043 | H212: 3/13/2025 | I212: 3 | J212: 195.63 | K212: 82.83 | L212: =_xlfn.XLOOKUP(F212,Products!$A$2:$A$51,Products!$D$2:$D$51,0) -> 65.21 | M212: =J212-K212 -> 112.8
A213: 7776fb61-e206-479a-a805-042f83d4e784 | B213: 3c11da88-1574-43bc-aeeb-a3913d2c26e5 | C213: =_xlfn.XLOOKUP(F213,Products!$A$2:$A$51,Products!$C$2:$C$51,0) -> Merchandise | D213: =_xlfn.XLOOKUP(F213,Products!$A$2:$A$51,Products!$B$2:$B$51,0) -> Minimalist Keychain | E213: =_xlfn.XLOOKUP(B213,customers!$A$2:$A$195,customers!$B$2:$B$195,,0) -> South | F213: 1020 | G213: =_xlfn.XLOOKUP(B213,customers!$A$1:$A$195,customers!$C$1:$C$195) -> 45054 | H213: 3/13/2025 | I213: 3 | J213: 82.11 | K213: 72.27 | L213: =_xlfn.XLOOKUP(F213,Products!$A$2:$A$51,Products!$D$2:$D$51,0) -> 27.37 | M213: =J213-K213 -> 9.84
A214: 7a347b2a-c8d1-417b-9896-6d35238ef4b6 | B214: 46ee2157-1365-44f4-ae66-e5855c3779d7 | C214: =_xlfn.XLOOKUP(F214,Products!$A$2:$A$51,Products!$C$2:$C$51,0) -> Consumables | D214: =_xlfn.XLOOKUP(F214,Products!$A$2:$A$51,Products!$B$2:$B$51,0) -> Single-Origin Ethiopian (250g) | E214: =_xlfn.XLOOKUP(B214,customers!$A$2:$A$195,customers!$B$2:$B$195,,0) -> East | F214: 1001 | G214: =_xlfn.XLOOKUP(B214,customers!$A$1:$A$195,customers!$C$1:$C$195) -> 45262 | H214: 3/13/2025 | I214: 4 | J214: 77.96 | K214: 50.82 | L214: =_xlfn.XLOOKUP(F214,Products!$A$2:$A$51,Products!$D$2:$D$51,0) -> 19.49 | M214: =J214-K214 -> 27.14
A215: 9687ae63-2ecc-4095-976c-d19cd16778f6 | B215: 0dbeb864-49cc-4ff3-9ccc-3edec157aba2 | C215: =_xlfn.XLOOKUP(F215,Products!$A$2:$A$51,Products!$C$2:$C$51,0) -> Merchandise | D215: =_xlfn.XLOOKUP(F215,Products!$A$2:$A$51,Products!$B$2:$B$51,0) -> Minimalist Keychain | E215: =_xlfn.XLOOKUP(B215,customers!$A$2:$A$195,customers!$B$2:$B$195,,0) -> North | F215: 1020 | G215: =_xlfn.XLOOKUP(B215,customers!$A$1:$A$195,customers!$C$1:$C$195) -> 45181 | H215: 3/14/2025 | I215: 3 | J215: 82.11 | K215: 72.27 | L215: =_xlfn.XLOOKUP(F215,Products!$A$2:$A$51,Products!$D$2:$D$51,0) -> 27.37 | M215: =J215-K215 -> 9.84
A216: 58df74b5-bf2d-484e-a91c-3b07a69d02d3 | B216: 72a4aaac-fd44-42a1-aaee-3e6c7cf309e2 | C216: =_xlfn.XLOOKUP(F216,Products!$A$2:$A$51,Products!$C$2:$C$51,0) -> Subscriptions | D216: =_xlfn.XLOOKUP(F216,Products!$A$2:$A$51,Products!$B$2:$B$51,0) -> Subscription Renewal Service | E216: =_xlfn.XLOOKUP(B216,customers!$A$2:$A$195,customers!$B$2:$B$195,,0) -> West | F216: 1025 | G216: =_xlfn.XLOOKUP(B216,customers!$A$1:$A$195,customers!$C$1:$C$195) -> 45164 | H216: 3/14/2025 | I216: 4 | J216: 293.64 | K216: 109.16 | L216: =_xlfn.XLOOKUP(F216,Products!$A$2:$A$51,Products!$D$2:$D$51,0) -> 73.41 | M216: =J216-K216 -> 184.48
A217: 5f67ef35-bcf6-437b-a246-a81d864edcda | B217: d245da28-64dc-4d8d-9d1f-6f6cab7abb85 | C217: =_xlfn.XLOOKUP(F217,Products!$A$2:$A$51,Products!$C$2:$C$51,0) -> Accessories | D217: =_xlfn.XLOOKUP(F217,Products!$A$2:$A$51,Products!$B$2:$B$51,0) -> Digital Coffee Scale | E217: =_xlfn.XLOOKUP(B217,customers!$A$2:$A$195,customers!$B$2:$B$195,,0) -> East | F217: 1036 | G217: =_xlfn.XLOOKUP(B217,customers!$A$1:$A$195,customers!$C$1:$C$195) -> 44976 | H217: 3/14/2025 | I217: 1 | J217: 26.83 | K217: 14.65 | L217: =_xlfn.XLOOKUP(F217,Products!$A$2:$A$51,Products!$D$2:$D$51,0) -> 26.83 | M217: =J217-K217 -> 12.18
A218: 3266f2c6-3900-4462-a018-cd86e58c58c6 | B218: 18bce6d7-de06-47c3-87dc-67dc5c8ffe62 | C218: =_xlfn.XLOOKUP(F218,Products!$A$2:$A$51,Products!$C$2:$C$51,0) -> Grinders & Brewers | D218: =_xlfn.XLOOKUP(F218,Products!$A$2:$A$51,Products!$B$2:$B$51,0) -> Precision Electric Grinder | E218: =_xlfn.XLOOKUP(B218,customers!$A$2:$A$195,customers!$B$2:$B$195,,0) -> North | F218: 1031 | G218: =_xlfn.XLOOKUP(B218,customers!$A$1:$A$195,customers!$C$1:$C$195) -> 45234 | H218: 3/14/2025 | I218: 1 | J218: 232.2 | K218: 78.39 | L218: =_xlfn.XLOOKUP(F218,Products!$A$2:$A$51,Products!$D$2:$D$51,0) -> 232.2 | M218: =J218-K218 -> 153.81
A219: 860991bc-0959-4846-85ef-77265f56feb5 | B219: b08475ba-c996-423d-9837-a8cde0c0e7ca | C219: =_xlfn.XLOOKUP(F219,Products!$A$2:$A$51,Products!$C$2:$C$51,0) -> Consumables | D219: =_xlfn.XLOOKUP(F219,Products!$A$2:$A$51,Products!$B$2:$B$51,0) -> Cold Brew Concentrate | E219: =_xlfn.XLOOKUP(B219,customers!$A$2:$A$195,customers!$B$2:$B$195,,0) -> South | F219: 1004 | G219: =_xlfn.XLOOKUP(B219,customers!$A$1:$A$195,customers!$C$1:$C$195) -> 45223 | H219: 3/15/2025 | I219: 2 | J219: 46.98 | K219: 20.17 | L219: =_xlfn.XLOOKUP(F219,Products!$A$2:$A$51,Products!$D$2:$D$51,0) -> 23.49 | M219: =J219-K219 -> 26.81
A220: ac57232e-3dc9-4b06-97cc-3f7b94dd137b | B220: 9db836e7-e5e0-4351-8a5a-37c082766fba | C220: =_xlfn.XLOOKUP(F220,Products!$A$2:$A$51,Products!$C$2:$C$51,0) -> Grinders & Brewers | D220: =_xlfn.XLOOKUP(F220,Products!$A$2:$A$51,Products!$B$2:$B$51,0) -> High-Capacity French Press | E220: =_xlfn.XLOOKUP(B220,customers!$A$2:$A$195,customers!$B$2:$B$195,,0) -> East | F220: 1009 | G220: =_xlfn.XLOOKUP(B220,customers!$A$1:$A$195,customers!$C$1:$C$195) -> 45055 | H220: 3/15/2025 | I220: 4 | J220: 1353.44 | K220: 592.68 | L220: =_xlfn.XLOOKUP(F220,Products!$A$2:$A$51,Products!$D$2:$D$51,0) -> 338.36 | M220: =J220-K220 -> 760.76
A221: a39d2cfd-9043-4cf0-9a50-24f6e60328fe | B221: 67435b8b-3191-4bd1-a143-8adb5039c70e | C221: =_xlfn.XLOOKUP(F221,Products!$A$2:$A$51,Products!$C$2:$C$51,0) -> Merchandise | D221: =_xlfn.XLOOKUP(F221,Products!$A$2:$A$51,Products!$B$2:$B$51,0) -> Insulated Travel Tumbler | E221: =_xlfn.XLOOKUP(B221,customers!$A$2:$A$195,customers!$B$2:$B$195,,0) -> West | F221: 1043 | G221: =_xlfn.XLOOKUP(B221,customers!$A$1:$A$195,customers!$C$1:$C$195) -> 45241 | H221: 3/16/2025 | I221: 3 | J221: 129.84 | K221: 62.47 | L221: =_xlfn.XLOOKUP(F221,Products!$A$2:$A$51,Products!$D$2:$D$51,0) -> 43.28 | M221: =J221-K221 -> 67.37
... A259: 3c87db83-208c-42f8-83ea-71f736f08f66 | B259: 5bc65488-8997-4f0b-9f7c-98bc3c2a66cd | C259: =_xlfn.XLOOKUP(F259,Products!$A$2:$A$51,Products!$C$2:$C$51,0) -> Consumables | D259: =_xlfn.XLOOKUP(F259,Products!$A$2:$A$51,Products!$B$2:$B$51,0) -> Decaf Blend (1kg) | E259: =_xlfn.XLOOKUP(B259,customers!$A$2:$A$195,customers!$B$2:$B$195,,0) -> East | F259: 1003 | G259: =_xlfn.XLOOKUP(B259,customers!$A$1:$A$195,customers!$C$1:$C$195) -> 45205 | H259: 3/27/2025 | I259: 4 | J259: 161.4 | K259: 51.44 | L259: =_xlfn.XLOOKUP(F259,Products!$A$2:$A$51,Products!$D$2:$D$51,0) -> 40.35 | M259: =J259-K259 -> 109.96
A260: e7223c67-a70d-4ac1-bc94-cbe1b1e77993 | B260: ac27451b-fbb6-4628-b02c-7f0aea75116c | C260: =_xlfn.XLOOKUP(F260,Products!$A$2:$A$51,Products!$C$2:$C$51,0) -> Grinders & Brewers | D260: =_xlfn.XLOOKUP(F260,Products!$A$2:$A$51,Products!$B$2:$B$51,0) -> Automated Drip Brewer | E260: East | F260: 1008 | G260: 45207 | H260: 3/27/2025 | I260: 1 | J260: 235.76 | K260: 132.48 | L260: =_xlfn.XLOOKUP(F260,Products!$A$2:$A$51,Products!$D$2:$D$51,0) -> 235.76 | M260: =J260-K260 -> 103.28
A261: bbb71e30-d217-4007-b3c6-48bda436704d | B261: 40ced29c-f517-4a8f-acaf-959ed0f3b156 | C261: =_xlfn.XLOOKUP(F261,Products!$A$2:$A$51,Products!$C$2:$C$51,0) -> Accessories | D261: =_xlfn.XLOOKUP(F261,Products!$A$2:$A$51,Products!$B$2:$B$51,0) -> Refillable Coffee Pods | E261: =_xlfn.XLOOKUP(B261,customers!$A$2:$A$195,customers!$B$2:$B$195,,0) -> South | F261: 1015 | G261: =_xlfn.XLOOKUP(B261,customers!$A$1:$A$195,customers!$C$1:$C$195) -> 45215 | H261: 3/27/2025 | I261: 2 | J261: 48.26 | K261: 18.59 | L261: =_xlfn.XLOOKUP(F261,Products!$A$2:$A$51,Products!$D$2:$D$51,0) -> 24.13 | M261: =J261-K261 -> 29.67
A262: 1eab32bd-3f6b-42ea-a583-40c1731d41ae | B262: 4661672e-252f-4297-8b05-ba339f296241 | C262: =_xlfn.XLOOKUP(F262,Products!$A$2:$A$51,Products!$C$2:$C$51,0) -> Subscriptions | D262: =_xlfn.XLOOKUP(F262,Products!$A$2:$A$51,Products!$B$2:$B$51,0) -> Subscription Renewal Service | E262: =_xlfn.XLOOKUP(B262,customers!$A$2:$A$195,customers!$B$2:$B$195,,0) -> West | F262: 1050 | G262: =_xlfn.XLOOKUP(B262,customers!$A$1:$A$195,customers!$C$1:$C$195) -> 44967 | H262: 3/28/2025 | I262: 2 | J262: 146.82 | K262: 54.58 | L262: =_xlfn.XLOOKUP(F262,Products!$A$2:$A$51,Products!$D$2:$D$51,0) -> 73.41 | M262: =J262-K262 -> 92.24
A263: c5641494-67c4-45b9-9ee3-24516aa16859 | B263: 889b8d90-6fd7-4dc5-b0d7-6fdce37da4c0 | C263: =_xlfn.XLOOKUP(F263,Products!$A$2:$A$51,Products!$C$2:$C$51,0) -> Subscriptions | D263: =_xlfn.XLOOKUP(F263,Products!$A$2:$A$51,Products!$B$2:$B$51,0) -> Espresso Lovers Quarterly Pack | E263: =_xlfn.XLOOKUP(B263,customers!$A$2:$A$195,customers!$B$2:$B$195,,0) -> North | F263: 1024 | G263: =_xlfn.XLOOKUP(B263,customers!$A$1:$A$195,customers!$C$1:$C$195) -> 45090 | H263: 3/28/2025 | I263: 2 | J263: 149.74 | K263: 38.39 | L263: =_xlfn.XLOOKUP(F263,Products!$A$2:$A$51,Products!$D$2:$D$51,0) -> 74.87 | M263: =J263-K263 -> 111.35
A264: 1c4a118f-3203-4812-a51f-e9ae35b1cefb | B264: f8ab10b6-1108-4ae2-a2b8-7cbdfe993a9a | C264: =_xlfn.XLOOKUP(F264,Products!$A$2:$A$51,Products!$C$2:$C$51,0) -> Consumables | D264: =_xlfn.XLOOKUP(F264,Products!$A$2:$A$51,Products!$B$2:$B$51,0) -> Decaf Blend (1kg) | E264: =_xlfn.XLOOKUP(B264,customers!$A$2:$A$195,customers!$B$2:$B$195,,0) -> East | F264: 1028 | G264: =_xlfn.XLOOKUP(B264,customers!$A$1:$A$195,customers!$C$1:$C$195) -> 45062 | H264: 3/28/2025 | I264: 2 | J264: 80.7 | K264: 25.72 | L264: =_xlfn.XLOOKUP(F264,Products!$A$2:$A$51,Products!$D$2:$D$51,0) -> 40.35 | M264: =J264-K264 -> 54.98
A265: 1dc623ac-15d4-47cc-8de3-27322a7d03dc | B265: 060e33b3-e9ae-4899-a3d3-d742591d183b | C265: =_xlfn.XLOOKUP(F265,Products!$A$2:$A$51,Products!$C$2:$C$51,0) -> Merchandise | D265: =_xlfn.XLOOKUP(F265,Products!$A$2:$A$51,Products!$B$2:$B$51,0) -> Logo Hoodie (Black) | E265: =_xlfn.XLOOKUP(B265,customers!$A$2:$A$195,customers!$B$2:$B$195,,0) -> South | F265: 1042 | G265: =_xlfn.XLOOKUP(B265,customers!$A$1:$A$195,customers!$C$1:$C$195) -> 45203 | H265: 3/28/2025 | I265: 1 | J265: 15.23 | K265: 13.4 | L265: =_xlfn.XLOOKUP(F265,Products!$A$2:$A$51,Products!$D$2:$D$51,0) -> 15.23 | M265: =J265-K265 -> 1.83
A266: c7cf5804-d7d6-4acc-ad39-fe1ee10e6439 | B266: 980d0516-288c-4e8a-8672-b19b88808fed | C266: =_xlfn.XLOOKUP(F266,Products!$A$2:$A$51,Products!$C$2:$C$51,0) -> Consumables | D266: =_xlfn.XLOOKUP(F266,Products!$A$2:$A$51,Products!$B$2:$B$51,0) -> Decaf Blend (1kg) | E266: =_xlfn.XLOOKUP(B266,customers!$A$2:$A$195,customers!$B$2:$B$195,,0) -> West | F266: 1028 | G266: =_xlfn.XLOOKUP(B266,customers!$A$1:$A$195,customers!$C$1:$C$195) -> 45269 | H266: 3/29/2025 | I266: 2 | J266: 80.7 | K266: 25.72 | L266: =_xlfn.XLOOKUP(F266,Products!$A$2:$A$51,Products!$D$2:$D$51,0) -> 40.35 | M266: =J266-K266 -> 54.98
A267: 6310e3b8-658d-4241-988e-b617b9fced8a | B267: 4c71f46b-aec0-4b76-92c5-beda74b59e13 | C267: =_xlfn.XLOOKUP(F267,Products!$A$2:$A$51,Products!$C$2:$C$51,0) -> Grinders & Brewers | D267: =_xlfn.XLOOKUP(F267,Products!$A$2:$A$51,Products!$B$2:$B$51,0) -> Hand Grinder (Travel Size) | E267: =_xlfn.XLOOKUP(B267,customers!$A$2:$A$195,customers!$B$2:$B$195,,0) -> West | F267: 1007 | G267: =_xlfn.XLOOKUP(B267,customers!$A$1:$A$195,customers!$C$1:$C$195) -> 45282 | H267: 3/30/2025 | I267: 3 | J267: 764.16 | K267: 390.85 | L267: =_xlfn.XLOOKUP(F267,Products!$A$2:$A$51,Products!$D$2:$D$51,0) -> 254.72 | M267: =J267-K267 -> 373.31
A268: a3936a6f-020e-4c85-8503-bc90aaf8f3dd | B268: 23781516-59fe-4b3b-af71-4d6cb8a012ad | C268: =_xlfn.XLOOKUP(F268,Products!$A$2:$A$51,Products!$C$2:$C$51,0) -> Consumables | D268: =_xlfn.XLOOKUP(F268,Products!$A$2:$A$51,Products!$B$2:$B$51,0) -> Cold Brew Concentrate | E268: =_xlfn.XLOOKUP(B268,customers!$A$2:$A$195,customers!$B$2:$B$195,,0) -> East | F268: 1029 | G268: =_xlfn.XLOOKUP(B268,customers!$A$1:$A$195,customers!$C$1:$C$195) -> 45214 | H268: 3/31/2025 | I268: 2 | J268: 46.98 | K268: 20.17 | L268: =_xlfn.XLOOKUP(F268,Products!$A$2:$A$51,Products!$D$2:$D$51,0) -> 23.49 | M268: =J268-K268 -> 26.81
A269: 9a1098d5-0376-4dad-81be-12da389ed215 | B269: 08d68de0-766e-42e3-9145-4e030f805140 | C269: =_xlfn.XLOOKUP(F269,Products!$A$2:$A$51,Products!$C$2:$C$51,0) -> Subscriptions | D269: =_xlfn.XLOOKUP(F269,Products!$A$2:$A$51,Products!$B$2:$B$51,0) -> Three-Month Gift Subscription | E269: =_xlfn.XLOOKUP(B269,customers!$A$2:$A$195,customers!$B$2:$B$195,,0) -> East | F269: 1048 | G269: =_xlfn.XLOOKUP(B269,customers!$A$1:$A$195,customers!$C$1:$C$195) -> 45253 | H269: 3/31/2025 | I269: 2 | J269: 130.42 | K269: 55.22 | L269: =_xlfn.XLOOKUP(F269,Products!$A$2:$A$51,Products!$D$2:$D$51,0) -> 65.21 | M269: =J269-K269 -> 75.2
A270: b56a4435-e59e-4980-851e-33aac53cf190 | B270: 060e33b3-e9ae-4899-a3d3-d742591d183b | C270: =_xlfn.XLOOKUP(F270,Products!$A$2:$A$51,Products!$C$2:$C$51,0) -> Consumables | D270: =_xlfn.XLOOKUP(F270,Products!$A$2:$A$51,Products!$B$2:$B$51,0) -> Cold Brew Concentrate | E270: =_xlfn.XLOOKUP(B270,customers!$A$2:$A$195,customers!$B$2:$B$195,,0) -> South | F270: 1029 | G270: =_xlfn.XLOOKUP(B270,customers!$A$1:$A$195,customers!$C$1:$C$195) -> 45203 | H270: 3/31/2025 | I270: 4 | J270: 93.96 | K270: 40.35 | L270: =_xlfn.XLOOKUP(F270,Products!$A$2:$A$51,Products!$D$2:$D$51,0) -> 23.49 | M270: =J270-K270 -> 53.61
A271: 166c3f4e-fb0f-442f-a3f8-a9170351648a | B271: b59d7d54-a0b9-4ba0-b2c4-b174c9f051a9 | C271: =_xlfn.XLOOKUP(F271,Products!$A$2:$A$51,Products!$C$2:$C$51,0) -> Grinders & Brewers | D271: =_xlfn.XLOOKUP(F271,Products!$A$2:$A$51,Products!$B$2:$B$51,0) -> Precision Electric Grinder | E271: =_xlfn.XLOOKUP(B271,customers!$A$2:$A$195,customers!$B$2:$B$195,,0) -> West | F271: 1031 | G271: =_xlfn.XLOOKUP(B271,customers!$A$1:$A$195,customers!$C$1:$C$195) -> 45206 | H271: 3/31/2025 | I271: 4 | J271: 928.8 | K271: 313.54 | L271: =_xlfn.XLOOKUP(F271,Products!$A$2:$A$51,Products!$D$2:$D$51,0) -> 232.2 | M271: =J271-K271 -> 615.26
A272: 97a3d9ff-f6d0-41ed-aa43-baec450445e1 | B272: ac87ecf7-ef9d-4b6a-84c4-7c1aa07eab14 | C272: =_xlfn.XLOOKUP(F272,Products!$A$2:$A$51,Products!$C$2:$C$51,0) -> Merchandise | D272: =_xlfn.XLOOKUP(F272,Products!$A$2:$A$51,Products!$B$2:$B$51,0) -> Branded Ceramic Mug (Large) | E272: =_xlfn.XLOOKUP(B272,customers!$A$2:$A$195,customers!$B$2:$B$195,,0) -> West | F272: 1041 | G272: =_xlfn.XLOOKUP(B272,customers!$A$1:$A$195,customers!$C$1:$C$195) -> 45010 | H272: 45661 | I272: 1 | J272: 43.2 | K272: 31.11 | L272: =_xlfn.XLOOKUP(F272,Products!$A$2:$A$51,Products!$D$2:$D$51,0) -> 43.2 | M272: =J272-K272 -> 12.09
A273: 4dd539c1-8e10-4ea2-98f9-78e36ec5410c | B273: db3b8c62-9cf3-448b-8e67-f6f0ad9cc3a6 | C273: =_xlfn.XLOOKUP(F273,Products!$A$2:$A$51,Products!$C$2:$C$51,0) -> Accessories | D273: =_xlfn.XLOOKUP(F273,Products!$A$2:$A$51,Products!$B$2:$B$51,0) -> Chemex Filters (100 pack) | E273: =_xlfn.XLOOKUP(B273,customers!$A$2:$A$195,customers!$B$2:$B$195,,0) -> West | F273: 1014 | G273: =_xlfn.XLOOKUP(B273,customers!$A$1:$A$195,customers!$C$1:$C$195) -> 45028 | H273: 45661 | I273: 1 | J273: 24.1 | K273: 21.21 | L273: =_xlfn.XLOOKUP(F273,Products!$A$2:$A$51,Products!$D$2:$D$51,0) -> 24.1 | M273: =J273-K273 -> 2.89
A274: 9c0d17fb-731d-4d38-9c91-d990fb13ece7 | B274: d72c51fa-89a1-4147-99f4-2dcf892fdbcc | C274: =_xlfn.XLOOKUP(F274,Products!$A$2:$A$51,Products!$C$2:$C$51,0) -> Merchandise | D274: =_xlfn.XLOOKUP(F274,Products!$A$2:$A$51,Products!$B$2:$B$51,0) -> Minimalist Keychain | E274: =_xlfn.XLOOKUP(B274,customers!$A$2:$A$195,customers!$B$2:$B$195,,0) -> North | F274: 1020 | G274: =_xlfn.XLOOKUP(B274,customers!$A$1:$A$195,customers!$C$1:$C$195) -> 45037 | H274: 45661 | I274: 3 | J274: 82.11 | K274: 72.27 | L274: =_xlfn.XLOOKUP(F274,Products!$A$2:$A$51,Products!$D$2:$D$51,0) -> 27.37 | M274: =J274-K274 -> 9.84
A275: 4ca1d9b4-1d1e-45e1-8054-09715838b9ef | B275: fcd08e95-2618-4bc4-9e53-a3a4cfe97e16 | C275: =_xlfn.XLOOKUP(F275,Products!$A$2:$A$51,Products!$C$2:$C$51,0) -> Merchandise | D275: =_xlfn.XLOOKUP(F275,Products!$A$2:$A$51,Products!$B$2:$B$51,0) -> Logo Hoodie (Black) | E275: =_xlfn.XLOOKUP(B275,customers!$A$2:$A$195,customers!$B$2:$B$195,,0) -> North | F275: 1017 | G275: =_xlfn.XLOOKUP(B275,customers!$A$1:$A$195,customers!$C$1:$C$195) -> 45129 | H275: 45661 | I275: 3 | J275: 45.69 | K275: 40.19 | L275: =_xlfn.XLOOKUP(F275,Products!$A$2:$A$51,Products!$D$2:$D$51,0) -> 15.23 | M275: =J275-K275 -> 5.5
A276: 95e72111-7deb-4459-a208-28593c7e07da | B276: f5d6f135-f651-402f-b38d-c5ec051c1e28 | C276: =_xlfn.XLOOKUP(F276,Products!$A$2:$A$51,Products!$C$2:$C$51,0) -> Grinders & Brewers | D276: =_xlfn.XLOOKUP(F276,Products!$A$2:$A$51,Products!$B$2:$B$51,0) -> Precision Electric Grinder | E276: =_xlfn.XLOOKUP(B276,customers!$A$2:$A$195,customers!$B$2:$B$195,,0) -> East | F276: 1031 | G276: =_xlfn.XLOOKUP(B276,customers!$A$1:$A$195,customers!$C$1:$C$195) -> 45139 | H276: 45661 | I276: 1 | J276: 232.2 | K276: 78.39 | L276: =_xlfn.XLOOKUP(F276,Products!$A$2:$A$51,Products!$D$2:$D$51,0) -> 232.2 | M276: =J276-K276 -> 153.81
A277: c321e333-0cc9-4166-9cbf-56a72336bada | B277: 31922566-0f17-4f1d-85c9-a5e5fc1d87a1 | C277: =_xlfn.XLOOKUP(F277,Products!$A$2:$A$51,Products!$C$2:$C$51,0) -> Grinders & Brewers | D277: =_xlfn.XLOOKUP(F277,Products!$A$2:$A$51,Products!$B$2:$B$51,0) -> Hand Grinder (Travel Size) | E277: =_xlfn.XLOOKUP(B277,customers!$A$2:$A$195,customers!$B$2:$B$195,,0) -> West | F277: 1032 | G277: =_xlfn.XLOOKUP(B277,customers!$A$1:$A$195,customers!$C$1:$C$195) -> 44955 | H277: 45661 | I277: 4 | J277: 1018.88 | K277: 521.14 | L277: =_xlfn.XLOOKUP(F277,Products!$A$2:$A$51,Products!$D$2:$D$51,0) -> 254.72 | M277: =J277-K277 -> 497.74
A278: 0e33b658-3488-4b20-a9d4-2c021a280b9e | B278: 46ee2157-1365-44f4-ae66-e5855c3779d7 | C278: =_xlfn.XLOOKUP(F278,Products!$A$2:$A$51,Products!$C$2:$C$51,0) -> Accessories | D278: =_xlfn.XLOOKUP(F278,Products!$A$2:$A$51,Products!$B$2:$B$51,0) -> Refillable Coffee Pods | E278: =_xlfn.XLOOKUP(B278,customers!$A$2:$A$195,customers!$B$2:$B$195,,0) -> East | F278: 1015 | G278: =_xlfn.XLOOKUP(B278,customers!$A$1:$A$195,customers!$C$1:$C$195) -> 45262 | H278: 45661 | I278: 3 | J278: 72.39 | K278: 27.88 | L278: =_xlfn.XLOOKUP(F278,Products!$A$2:$A$51,Products!$D$2:$D$51,0) -> 24.13 | M278: =J278-K278 -> 44.51
A279: 7e003ab9-d22f-49bd-8017-252fae3868d1 | B279: 524e9631-7dc4-489e-94e2-7b12f7cbc615 | C279: =_xlfn.XLOOKUP(F279,Products!$A$2:$A$51,Products!$C$2:$C$51,0) -> Grinders & Brewers | D279: =_xlfn.XLOOKUP(F279,Products!$A$2:$A$51,Products!$B$2:$B$51,0) -> High-Capacity French Press | E279: =_xlfn.XLOOKUP(B279,customers!$A$2:$A$195,customers!$B$2:$B$195,,0) -> South | F279: 1009 | G279: =_xlfn.XLOOKUP(B279,customers!$A$1:$A$195,customers!$C$1:$C$195) -> 45288 | H279: 45661 | I279: 4 | J279: 1353.44 | K279: 592.68 | L279: =_xlfn.XLOOKUP(F279,Products!$A$2:$A$51,Products!$D$2:$D$51,0) -> 338.36 | M279: =J279-K279 -> 760.76
A280: b8f3e004-671a-4675-b239-e4dd30659b45 | B280: 82df6f1e-6e7d-40cd-aec0-e796f8f27a63 | C280: =_xlfn.XLOOKUP(F280,Products!$A$2:$A$51,Products!$C$2:$C$51,0) -> Subscriptions | D280: =_xlfn.XLOOKUP(F280,Products!$A$2:$A$51,Products!$B$2:$B$51,0) -> Espresso Lovers Quarterly Pack | E280: =_xlfn.XLOOKUP(B280,customers!$A$2:$A$195,customers!$B$2:$B$195,,0) -> East | F280: 1049 | G280: =_xlfn.XLOOKUP(B280,customers!$A$1:$A$195,customers!$C$1:$C$195) -> 45112 | H280: 45692 | I280: 3 | J280: 224.61 | K280: 57.58 | L280: =_xlfn.XLOOKUP(F280,Products!$A$2:$A$51,Products!$D$2:$D$51,0) -> 74.87 | M280: =J280-K280 -> 167.03
...

Sheet Pivot Table
A3: CustomerID | B3: Max of OrderDate | C3: Distinct Count of OrderID | D3: Sum of Revenue
A4: 006bc8ad-8e59-4d6f-ab38-475a02a0f952 | B4: 45785 | C4: 8 | D4: 1248.55
A5: 019d6740-e346-47b9-b042-acab3646d400 | B5: 45843 | C5: 10 | D5: 825.56
A6: 01ab4a79-7c36-4fc3-93b9-758bf5edbd00 | B6: 45969 | C6: 8 | D6: 1953.64
A7: 0518f99d-8e5b-496f-9c0b-34f0c24ee49f | B7: 45932 | C7: 6 | D7: 1068.08
A8: 060e33b3-e9ae-4899-a3d3-d742591d183b | B8: 46000 | C8: 9 | D8: 874.11
A9: 06ea8b50-0535-4c29-bc28-ff3c7c4ba7b8 | B9: 45844 | C9: 4 | D9: 547.76
A10: 08d68de0-766e-42e3-9145-4e030f805140 | B10: 45964 | C10: 3 | D10: 884.9
A11: 0a5d8031-b5a7-4be4-8d5d-63b70f2a67c7 | B11: 45845 | C11: 9 | D11: 1149.37
A12: 0aca39d0-c1c9-450c-bf56-9026ed1420ff | B12: 45873 | C12: 4 | D12: 392.22
A13: 0b59de48-4882-496e-98d7-a9053fe88877 | B13: 45756 | C13: 7 | D13: 1515.61
A14: 0dbeb864-49cc-4ff3-9ccc-3edec157aba2 | B14: 45843 | C14: 7 | D14: 2506.47
A15: 0e025dda-dcfd-4349-b45d-994ba4664cb3 | B15: 45970 | C15: 8 | D15: 943.09
... A183: Grand Total | B183: 46002 | C183: 1158 | D183: 235738.29

Sheet RFM Analysis
B1: Max Date | C1: =DATE(2025,12,15) -> 46006
A3: CustomerID | B3: Last Date of Purchase | C3: Recency | D3: Frequency | E3: Monetary | F3: R Score | G3: F Score | H3: M Score | I3: RFM Score | J3: RFM Segment
A4: 006bc8ad-8e59-4d6f-ab38-475a02a0f952 | B4: 45785 | C4: =DATEDIF(B4,$C$1,"d") -> 221 | D4: 8 | E4: 1248.55 | F4: =ROUND((1-_xlfn.PERCENTRANK.INC($C$4:$C$182,C4))*9,0) -> 1 | G4: =ROUND((1-_xlfn.PERCENTRANK.INC($D$4:$D$182,D4))*9,0) -> 3 | H4: =ROUND((1-_xlfn.PERCENTRANK.INC($E$4:$E$182,E4))*9,0) -> 4 | I4: =CONCATENATE(F4,G4,H4) -> 134 | J4: {=_xlfn.IFS(AND(F4>=8,G4>=8,H4>=8),"Champion",AND(F4>=6,G4>=7,H4>=6),"Loyal Customer",AND(F4>=6,G4>=5,H4>=5),"Potential Loyalist",AND(F4>=8,G4>=2,H4>=5),"New Customers",AND(F4>=6,G4>=2,H4>=3),"Promising",AND(F4>=3,G4>=3,H4>=3),"Need Attention",AND(F4>=4,G4>=6,H4>=6),"At Risk",AND(F4>=2,G4>=8,H4>=8),"Can't Lose Them",AND(F4>=2,G4>=2,H4>=2),"Hibernating",TRUE,"Other")} -> Other
A5: 019d6740-e346-47b9-b042-acab3646d400 | B5: 45843 | C5: =DATEDIF(B5,$C$1,"d") -> 163 | D5: 10 | E5: 825.56 | F5: =ROUND((1-_xlfn.PERCENTRANK.INC($C$4:$C$182,C5))*9,0) -> 2 | G5: =ROUND((1-_xlfn.PERCENTRANK.INC($D$4:$D$182,D5))*9,0) -> 0 | H5: =ROUND((1-_xlfn.PERCENTRANK.INC($E$4:$E$182,E5))*9,0) -> 6 | I5: =CONCATENATE(F5,G5,H5) -> 206 | J5: {=_xlfn.IFS(AND(F5>=8,G5>=8,H5>=8),"Champion",AND(F5>=6,G5>=7,H5>=6),"Loyal Customer",AND(F5>=6,G5>=5,H5>=5),"Potential Loyalist",AND(F5>=8,G5>=2,H5>=5),"New Customers",AND(F5>=6,G5>=2,H5>=3),"Promising",AND(F5>=3,G5>=3,H5>=3),"Need Attention",AND(F5>=4,G5>=6,H5>=6),"At Risk",AND(F5>=2,G5>=8,H5>=8),"Can't Lose Them",AND(F5>=2,G5>=2,H5>=2),"Hibernating",TRUE,"Other")} -> Other
A6: 01ab4a79-7c36-4fc3-93b9-758bf5edbd00 | B6: 45969 | C6: =DATEDIF(B6,$C$1,"d") -> 37 | D6: 8 | E6: 1953.64 | F6: =ROUND((1-_xlfn.PERCENTRANK.INC($C$4:$C$182,C6))*9,0) -> 7 | G6: =ROUND((1-_xlfn.PERCENTRANK.INC($D$4:$D$182,D6))*9,0) -> 3 | H6: =ROUND((1-_xlfn.PERCENTRANK.INC($E$4:$E$182,E6))*9,0) -> 2 | I6: =CONCATENATE(F6,G6,H6) -> 732 | J6: {=_xlfn.IFS(AND(F6>=8,G6>=8,H6>=8),"Champion",AND(F6>=6,G6>=7,H6>=6),"Loyal Customer",AND(F6>=6,G6>=5,H6>=5),"Potential Loyalist",AND(F6>=8,G6>=2,H6>=5),"New Customers",AND(F6>=6,G6>=2,H6>=3),"Promising",AND(F6>=3,G6>=3,H6>=3),"Need Attention",AND(F6>=4,G6>=6,H6>=6),"At Risk",AND(F6>=2,G6>=8,H6>=8),"Can't Lose Them",AND(F6>=2,G6>=2,H6>=2),"Hibernating",TRUE,"Other")} -> Hibernating
A7: 0518f99d-8e5b-496f-9c0b-34f0c24ee49f | B7: 45932 | C7: =DATEDIF(B7,$C$1,"d") -> 74 | D7: 6 | E7: 1068.08 | F7: =ROUND((1-_xlfn.PERCENTRANK.INC($C$4:$C$182,C7))*9,0) -> 5 | G7: =ROUND((1-_xlfn.PERCENTRANK.INC($D$4:$D$182,D7))*9,0) -> 6 | H7: =ROUND((1-_xlfn.PERCENTRANK.INC($E$4:$E$182,E7))*9,0) -> 5 | I7: =CONCATENATE(F7,G7,H7) -> 565 | J7: {=_xlfn.IFS(AND(F7>=8,G7>=8,H7>=8),"Champion",AND(F7>=6,G7>=7,H7>=6),"Loyal Customer",AND(F7>=6,G7>=5,H7>=5),"Potential Loyalist",AND(F7>=8,G7>=2,H7>=5),"New Customers",AND(F7>=6,G7>=2,H7>=3),"Promising",AND(F7>=3,G7>=3,H7>=3),"Need Attention",AND(F7>=4,G7>=6,H7>=6),"At Risk",AND(F7>=2,G7>=8,H7>=8),"Can't Lose Them",AND(F7>=2,G7>=2,H7>=2),"Hibernating",TRUE,"Other")} -> Need Attention
A8: 060e33b3-e9ae-4899-a3d3-d742591d183b | B8: 46000 | C8: =DATEDIF(B8,$C$1,"d") -> 6 | D8: 9 | E8: 874.11 | F8: =ROUND((1-_xlfn.PERCENTRANK.INC($C$4:$C$182,C8))*9,0) -> 9 | G8: =ROUND((1-_xlfn.PERCENTRANK.INC($D$4:$D$182,D8))*9,0) -> 2 | H8: =ROUND((1-_xlfn.PERCENTRANK.INC($E$4:$E$182,E8))*9,0) -> 6 | I8: =CONCATENATE(F8,G8,H8) -> 926 | J8: {=_xlfn.IFS(AND(F8>=8,G8>=8,H8>=8),"Champion",AND(F8>=6,G8>=7,H8>=6),"Loyal Customer",AND(F8>=6,G8>=5,H8>=5),"Potential Loyalist",AND(F8>=8,G8>=2,H8>=5),"New Customers",AND(F8>=6,G8>=2,H8>=3),"Promising",AND(F8>=3,G8>=3,H8>=3),"Need Attention",AND(F8>=4,G8>=6,H8>=6),"At Risk",AND(F8>=2,G8>=8,H8>=8),"Can't Lose Them",AND(F8>=2,G8>=2,H8>=2),"Hibernating",TRUE,"Other")} -> New Customers
A9: 06ea8b50-0535-4c29-bc28-ff3c7c4ba7b8 | B9: 45844 | C9: =DATEDIF(B9,$C$1,"d") -> 162 | D9: 4 | E9: 547.76 | F9: =ROUND((1-_xlfn.PERCENTRANK.INC($C$4:$C$182,C9))*9,0) -> 2 | G9: =ROUND((1-_xlfn.PERCENTRANK.INC($D$4:$D$182,D9))*9,0) -> 8 | H9: =ROUND((1-_xlfn.PERCENTRANK.INC($E$4:$E$182,E9))*9,0) -> 8 | I9: =CONCATENATE(F9,G9,H9) -> 288 | J9: {=_xlfn.IFS(AND(F9>=8,G9>=8,H9>=8),"Champion",AND(F9>=6,G9>=7,H9>=6),"Loyal Customer",AND(F9>=6,G9>=5,H9>=5),"Potential Loyalist",AND(F9>=8,G9>=2,H9>=5),"New Customers",AND(F9>=6,G9>=2,H9>=3),"Promising",AND(F9>=3,G9>=3,H9>=3),"Need Attention",AND(F9>=4,G9>=6,H9>=6),"At Risk",AND(F9>=2,G9>=8,H9>=8),"Can't Lose Them",AND(F9>=2,G9>=2,H9>=2),"Hibernating",TRUE,"Other")} -> Can't Lose Them
A10: 08d68de0-766e-42e3-9145-4e030f805140 | B10: 45964 | C10: =DATEDIF(B10,$C$1,"d") -> 42 | D10: 3 | E10: 884.9 | F10: =ROUND((1-_xlfn.PERCENTRANK.INC($C$4:$C$182,C10))*9,0) -> 6 | G10: =ROUND((1-_xlfn.PERCENTRANK.INC($D$4:$D$182,D10))*9,0) -> 9 | H10: =ROUND((1-_xlfn.PERCENTRANK.INC($E$4:$E$182,E10))*9,0) -> 6 | I10: =CONCATENATE(F10,G10,H10) -> 696 | J10: {=_xlfn.IFS(AND(F10>=8,G10>=8,H10>=8),"Champion",AND(F10>=6,G10>=7,H10>=6),"Loyal Customer",AND(F10>=6,G10>=5,H10>=5),"Potential Loyalist",AND(F10>=8,G10>=2,H10>=5),"New Customers",AND(F10>=6,G10>=2,H10>=3),"Promising",AND(F10>=3,G10>=3,H10>=3),"Need Attention",AND(F10>=4,G10>=6,H10>=6),"At Risk",AND(F10>=2,G10>=8,H10>=8),"Can't Lose Them",AND(F10>=2,G10>=2,H10>=2),"Hibernating",TRUE,"Other")} -> Loyal Customer
A11: 0a5d8031-b5a7-4be4-8d5d-63b70f2a67c7 | B11: 45845 | C11: =DATEDIF(B11,$C$1,"d") -> 161 | D11: 9 | E11: 1149.37 | F11: =ROUND((1-_xlfn.PERCENTRANK.INC($C$4:$C$182,C11))*9,0) -> 2 | G11: =ROUND((1-_xlfn.PERCENTRANK.INC($D$4:$D$182,D11))*9,0) -> 2 | H11: =ROUND((1-_xlfn.PERCENTRANK.INC($E$4:$E$182,E11))*9,0) -> 5 | I11: =CONCATENATE(F11,G11,H11) -> 225 | J11: {=_xlfn.IFS(AND(F11>=8,G11>=8,H11>=8),"Champion",AND(F11>=6,G11>=7,H11>=6),"Loyal Customer",AND(F11>=6,G11>=5,H11>=5),"Potential Loyalist",AND(F11>=8,G11>=2,H11>=5),"New Customers",AND(F11>=6,G11>=2,H11>=3),"Promising",AND(F11>=3,G11>=3,H11>=3),"Need Attention",AND(F11>=4,G11>=6,H11>=6),"At Risk",AND(F11>=2,G11>=8,H11>=8),"Can't Lose Them",AND(F11>=2,G11>=2,H11>=2),"Hibernating",TRUE,"Other")} -> Hibernating
A12: 0aca39d0-c1c9-450c-bf56-9026ed1420ff | B12: 45873 | C12: =DATEDIF(B12,$C$1,"d") -> 133 | D12: 4 | E12: 392.22 | F12: =ROUND((1-_xlfn.PERCENTRANK.INC($C$4:$C$182,C12))*9,0) -> 3 | G12: =ROUND((1-_xlfn.PERCENTRANK.INC($D$4:$D$182,D12))*9,0) -> 8 | H12: =ROUND((1-_xlfn.PERCENTRANK.INC($E$4:$E$182,E12))*9,0) -> 8 | I12: =CONCATENATE(F12,G12,H12) -> 388 | J12: {=_xlfn.IFS(AND(F12>=8,G12>=8,H12>=8),"Champion",AND(F12>=6,G12>=7,H12>=6),"Loyal Customer",AND(F12>=6,G12>=5,H12>=5),"Potential Loyalist",AND(F12>=8,G12>=2,H12>=5),"New Customers",AND(F12>=6,G12>=2,H12>=3),"Promising",AND(F12>=3,G12>=3,H12>=3),"Need Attention",AND(F12>=4,G12>=6,H12>=6),"At Risk",AND(F12>=2,G12>=8,H12>=8),"Can't Lose Them",AND(F12>=2,G12>=2,H12>=2),"Hibernating",TRUE,"Other")} -> Need Attention
A13: 0b59de48-4882-496e-98d7-a9053fe88877 | B13: 45756 | C13: =DATEDIF(B13,$C$1,"d") -> 250 | D13: 7 | E13: 1515.61 | F13: =ROUND((1-_xlfn.PERCENTRANK.INC($C$4:$C$182,C13))*9,0) -> 1 | G13: =ROUND((1-_xlfn.PERCENTRANK.INC($D$4:$D$182,D13))*9,0) -> 4 | H13: =ROUND((1-_xlfn.PERCENTRANK.INC($E$4:$E$182,E13))*9,0) -> 3 | I13: =CONCATENATE(F13,G13,H13) -> 143 | J13: {=_xlfn.IFS(AND(F13>=8,G13>=8,H13>=8),"Champion",AND(F13>=6,G13>=7,H13>=6),"Loyal Customer",AND(F13>=6,G13>=5,H13>=5),"Potential Loyalist",AND(F13>=8,G13>=2,H13>=5),"New Customers",AND(F13>=6,G13>=2,H13>=3),"Promising",AND(F13>=3,G13>=3,H13>=3),"Need Attention",AND(F13>=4,G13>=6,H13>=6),"At Risk",AND(F13>=2,G13>=8,H13>=8),"Can't Lose Them",AND(F13>=2,G13>=2,H13>=2),"Hibernating",TRUE,"Other")} -> Other
A14: 0dbeb864-49cc-4ff3-9ccc-3edec157aba2 | B14: 45843 | C14: =DATEDIF(B14,$C$1,"d") -> 163 | D14: 7 | E14: 2506.47 | F14: =ROUND((1-_xlfn.PERCENTRANK.INC($C$4:$C$182,C14))*9,0) -> 2 | G14: =ROUND((1-_xlfn.PERCENTRANK.INC($D$4:$D$182,D14))*9,0) -> 4 | H14: =ROUND((1-_xlfn.PERCENTRANK.INC($E$4:$E$182,E14))*9,0) -> 1 | I14: =CONCATENATE(F14,G14,H14) -> 241 | J14: {=_xlfn.IFS(AND(F14>=8,G14>=8,H14>=8),"Champion",AND(F14>=6,G14>=7,H14>=6),"Loyal Customer",AND(F14>=6,G14>=5,H14>=5),"Potential Loyalist",AND(F14>=8,G14>=2,H14>=5),"New Customers",AND(F14>=6,G14>=2,H14>=3),"Promising",AND(F14>=3,G14>=3,H14>=3),"Need Attention",AND(F14>=4,G14>=6,H14>=6),"At Risk",AND(F14>=2,G14>=8,H14>=8),"Can't Lose Them",AND(F14>=2,G14>=2,H14>=2),"Hibernating",TRUE,"Other")} -> Other
A15: 0e025dda-dcfd-4349-b45d-994ba4664cb3 | B15: 45970 | C15: =DATEDIF(B15,$C$1,"d") -> 36 | D15: 8 | E15: 943.09 | F15: =ROUND((1-_xlfn.PERCENTRANK.INC($C$4:$C$182,C15))*9,0) -> 7 | G15: =ROUND((1-_xlfn.PERCENTRANK.INC($D$4:$D$182,D15))*9,0) -> 3 | H15: =ROUND((1-_xlfn.PERCENTRANK.INC($E$4:$E$182,E15))*9,0) -> 6 | I15: =CONCATENATE(F15,G15,H15) -> 736 | J15: {=_xlfn.IFS(AND(F15>=8,G15>=8,H15>=8),"Champion",AND(F15>=6,G15>=7,H15>=6),"Loyal Customer",AND(F15>=6,G15>=5,H15>=5),"Potential Loyalist",AND(F15>=8,G15>=2,H15>=5),"New Customers",AND(F15>=6,G15>=2,H15>=3),"Promising",AND(F15>=3,G15>=3,H15>=3),"Need Attention",AND(F15>=4,G15>=6,H15>=6),"At Risk",AND(F15>=2,G15>=8,H15>=8),"Can't Lose Them",AND(F15>=2,G15>=2,H15>=2),"Hibernating",TRUE,"Other")} -> Promising
... A182: ff2be8d4-a06b-4c87-aefa-1f4020ebc0e2 | B182: 45814 | C182: =DATEDIF(B182,$C$1,"d") -> 192 | D182: 9 | E182: 2266.37 | F182: =ROUND((1-_xlfn.PERCENTRANK.INC($C$4:$C$182,C182))*9,0) -> 2 | G182: =ROUND((1-_xlfn.PERCENTRANK.INC($D$4:$D$182,D182))*9,0) -> 2 | H182: =ROUND((1-_xlfn.PERCENTRANK.INC($E$4:$E$182,E182))*9,0) -> 1 | I182: =CONCATENATE(F182,G182,H182) -> 221 | J182: {=_xlfn.IFS(AND(F182>=8,G182>=8,H182>=8),"Champion",AND(F182>=6,G182>=7,H182>=6),"Loyal Customer",AND(F182>=6,G182>=5,H182>=5),"Potential Loyalist",AND(F182>=8,G182>=2,H182>=5),"New Customers",AND(F182>=6,G182>=2,H182>=3),"Promising",AND(F182>=3,G182>=3,H182>=3),"Need Attention",AND(F182>=4,G182>=6,H182>=6),"At Risk",AND(F182>=2,G182>=8,H182>=8),"Can't Lose Them",AND(F182>=2,G182>=2,H182>=2),"Hibernating",TRUE,"Other")} -> Other

Sheet Customer Segmentation
A12: Segment | B12: Customer Count
A13: Other | B13: =COUNTIFS('RFM Analysis'!J3:$J$182,A13) -> 63
A14: Need Attention | B14: =COUNTIFS('RFM Analysis'!J4:$J$182,A14) -> 32
A15: Hibernating | B15: =COUNTIFS('RFM Analysis'!J5:$J$182,A15) -> 30
A16: Promising | B16: =COUNTIFS('RFM Analysis'!J6:$J$182,A16) -> 18
A17: Loyal Customer | B17: =COUNTIFS('RFM Analysis'!J7:$J$182,A17) -> 13
A18: Potential Loyalist | B18: =COUNTIFS('RFM Analysis'!J8:$J$182,A18) -> 11
A19: New Customers | B19: =COUNTIFS('RFM Analysis'!J9:$J$182,A19) -> 6
A20: Champion | B20: =COUNTIFS('RFM Analysis'!J10:$J$182,A20) -> 3
A21: At Risk | B21: =COUNTIFS('RFM Analysis'!J11:$J$182,A21) -> 0
A22: Segments | B22: Definition Of Segments | C22: Strategy
A23: Cant lose them | B23: Former regular customers who have stopped buying | C23: Offer exclusive reactivation campaigns and get feedback
A24: Champion | B24: Your best customers who recently purchased, buy | C24: Give exclusive offers and early access to new products
B25: frequently and spend the most
A26: Hibernating | B26: Haven't purchased in a long time and were once active | C26: Offer small, target promotions to wake them up without
C27: significant expenditure
A28: Loyal | B28: They are frequent purchasers | C28: Offer loyalty programs, complementary products and
C29: encourage higher spending through bundle deals.
A30: Need attention | B30: Haven't bought for a long time and are not big spenders | C30: Win them back with re-engagement campaigns or deals
A31: New Customer | B31: Just made their first or early purchase | C31: Build trust by post-purchase communication and offer
C32: discount for second purchase
A33: Potential loyalists | B33: Recent customers with average frequency but good | C33: Send follow-up offers, welcome series emails and value
B34: spending | C34: propositions
A35: Promising | B35: Recent customers who have potential but haven't | C35: Focus on building loyalty and encouraging repeat purchase
B36: bought much yet
A37: At Risk | B37: Customers who purchase frequently and are big | C37: Use win back campaigns with strong incentives, share informative
B38: spenders but haven't made a purchase recently | C38: and entertaining content via social media platforms
